package com.google.i18n.phonenumbers;

public class CountryCodeToRegionCodeMap
{
  // ERROR //
  static java.util.Map<java.lang.Integer, java.util.List<java.lang.String>> getCountryCodeToRegionCodeMap()
  {
    // Byte code:
    //   0: new 12	java/util/HashMap
    //   3: dup
    //   4: sipush 286
    //   7: invokespecial 15	java/util/HashMap:<init>	(I)V
    //   10: astore_0
    //   11: new 17	java/util/ArrayList
    //   14: dup
    //   15: bipush 25
    //   17: invokespecial 18	java/util/ArrayList:<init>	(I)V
    //   20: astore_1
    //   21: aload_1
    //   22: ldc 20
    //   24: invokevirtual 24	java/util/ArrayList:add	(Ljava/lang/Object;)Z
    //   27: pop
    //   28: aload_1
    //   29: ldc 26
    //   31: invokevirtual 24	java/util/ArrayList:add	(Ljava/lang/Object;)Z
    //   34: pop
    //   35: aload_1
    //   36: ldc 28
    //   38: invokevirtual 24	java/util/ArrayList:add	(Ljava/lang/Object;)Z
    //   41: pop
    //   42: aload_1
    //   43: ldc 30
    //   45: invokevirtual 24	java/util/ArrayList:add	(Ljava/lang/Object;)Z
    //   48: pop
    //   49: aload_1
    //   50: ldc 32
    //   52: invokevirtual 24	java/util/ArrayList:add	(Ljava/lang/Object;)Z
    //   55: pop
    //   56: aload_1
    //   57: ldc 34
    //   59: invokevirtual 24	java/util/ArrayList:add	(Ljava/lang/Object;)Z
    //   62: pop
    //   63: aload_1
    //   64: ldc 36
    //   66: invokevirtual 24	java/util/ArrayList:add	(Ljava/lang/Object;)Z
    //   69: pop
    //   70: aload_1
    //   71: ldc 38
    //   73: invokevirtual 24	java/util/ArrayList:add	(Ljava/lang/Object;)Z
    //   76: pop
    //   77: aload_1
    //   78: ldc 40
    //   80: invokevirtual 24	java/util/ArrayList:add	(Ljava/lang/Object;)Z
    //   83: pop
    //   84: aload_1
    //   85: ldc 42
    //   87: invokevirtual 24	java/util/ArrayList:add	(Ljava/lang/Object;)Z
    //   90: pop
    //   91: aload_1
    //   92: ldc 44
    //   94: invokevirtual 24	java/util/ArrayList:add	(Ljava/lang/Object;)Z
    //   97: pop
    //   98: aload_1
    //   99: ldc 46
    //   101: invokevirtual 24	java/util/ArrayList:add	(Ljava/lang/Object;)Z
    //   104: pop
    //   105: aload_1
    //   106: ldc 48
    //   108: invokevirtual 24	java/util/ArrayList:add	(Ljava/lang/Object;)Z
    //   111: pop
    //   112: aload_1
    //   113: ldc 50
    //   115: invokevirtual 24	java/util/ArrayList:add	(Ljava/lang/Object;)Z
    //   118: pop
    //   119: aload_1
    //   120: ldc 52
    //   122: invokevirtual 24	java/util/ArrayList:add	(Ljava/lang/Object;)Z
    //   125: pop
    //   126: aload_1
    //   127: ldc 54
    //   129: invokevirtual 24	java/util/ArrayList:add	(Ljava/lang/Object;)Z
    //   132: pop
    //   133: aload_1
    //   134: ldc 56
    //   136: invokevirtual 24	java/util/ArrayList:add	(Ljava/lang/Object;)Z
    //   139: pop
    //   140: aload_1
    //   141: ldc 58
    //   143: invokevirtual 24	java/util/ArrayList:add	(Ljava/lang/Object;)Z
    //   146: pop
    //   147: aload_1
    //   148: ldc 60
    //   150: invokevirtual 24	java/util/ArrayList:add	(Ljava/lang/Object;)Z
    //   153: pop
    //   154: aload_1
    //   155: ldc 62
    //   157: invokevirtual 24	java/util/ArrayList:add	(Ljava/lang/Object;)Z
    //   160: pop
    //   161: aload_1
    //   162: ldc 64
    //   164: invokevirtual 24	java/util/ArrayList:add	(Ljava/lang/Object;)Z
    //   167: pop
    //   168: aload_1
    //   169: ldc 66
    //   171: invokevirtual 24	java/util/ArrayList:add	(Ljava/lang/Object;)Z
    //   174: pop
    //   175: aload_1
    //   176: ldc 68
    //   178: invokevirtual 24	java/util/ArrayList:add	(Ljava/lang/Object;)Z
    //   181: pop
    //   182: aload_1
    //   183: ldc 70
    //   185: invokevirtual 24	java/util/ArrayList:add	(Ljava/lang/Object;)Z
    //   188: pop
    //   189: aload_1
    //   190: ldc 72
    //   192: invokevirtual 24	java/util/ArrayList:add	(Ljava/lang/Object;)Z
    //   195: pop
    //   196: aload_0
    //   197: iconst_1
    //   198: invokestatic 78	java/lang/Integer:valueOf	(I)Ljava/lang/Integer;
    //   201: aload_1
    //   202: invokeinterface 84 3 0
    //   207: pop
    //   208: new 17	java/util/ArrayList
    //   211: dup
    //   212: iconst_2
    //   213: invokespecial 18	java/util/ArrayList:<init>	(I)V
    //   216: astore 28
    //   218: aload 28
    //   220: ldc 86
    //   222: invokevirtual 24	java/util/ArrayList:add	(Ljava/lang/Object;)Z
    //   225: pop
    //   226: aload 28
    //   228: ldc 88
    //   230: invokevirtual 24	java/util/ArrayList:add	(Ljava/lang/Object;)Z
    //   233: pop
    //   234: aload_0
    //   235: bipush 7
    //   237: invokestatic 78	java/lang/Integer:valueOf	(I)Ljava/lang/Integer;
    //   240: aload 28
    //   242: invokeinterface 84 3 0
    //   247: pop
    //   248: new 17	java/util/ArrayList
    //   251: dup
    //   252: iconst_1
    //   253: invokespecial 18	java/util/ArrayList:<init>	(I)V
    //   256: astore 32
    //   258: aload 32
    //   260: ldc 90
    //   262: invokevirtual 24	java/util/ArrayList:add	(Ljava/lang/Object;)Z
    //   265: pop
    //   266: aload_0
    //   267: bipush 20
    //   269: invokestatic 78	java/lang/Integer:valueOf	(I)Ljava/lang/Integer;
    //   272: aload 32
    //   274: invokeinterface 84 3 0
    //   279: pop
    //   280: new 17	java/util/ArrayList
    //   283: dup
    //   284: iconst_1
    //   285: invokespecial 18	java/util/ArrayList:<init>	(I)V
    //   288: astore 35
    //   290: aload 35
    //   292: ldc 92
    //   294: invokevirtual 24	java/util/ArrayList:add	(Ljava/lang/Object;)Z
    //   297: pop
    //   298: aload_0
    //   299: bipush 27
    //   301: invokestatic 78	java/lang/Integer:valueOf	(I)Ljava/lang/Integer;
    //   304: aload 35
    //   306: invokeinterface 84 3 0
    //   311: pop
    //   312: new 17	java/util/ArrayList
    //   315: dup
    //   316: iconst_1
    //   317: invokespecial 18	java/util/ArrayList:<init>	(I)V
    //   320: astore 38
    //   322: aload 38
    //   324: ldc 94
    //   326: invokevirtual 24	java/util/ArrayList:add	(Ljava/lang/Object;)Z
    //   329: pop
    //   330: aload_0
    //   331: bipush 30
    //   333: invokestatic 78	java/lang/Integer:valueOf	(I)Ljava/lang/Integer;
    //   336: aload 38
    //   338: invokeinterface 84 3 0
    //   343: pop
    //   344: new 17	java/util/ArrayList
    //   347: dup
    //   348: iconst_1
    //   349: invokespecial 18	java/util/ArrayList:<init>	(I)V
    //   352: astore 41
    //   354: aload 41
    //   356: ldc 96
    //   358: invokevirtual 24	java/util/ArrayList:add	(Ljava/lang/Object;)Z
    //   361: pop
    //   362: aload_0
    //   363: bipush 31
    //   365: invokestatic 78	java/lang/Integer:valueOf	(I)Ljava/lang/Integer;
    //   368: aload 41
    //   370: invokeinterface 84 3 0
    //   375: pop
    //   376: new 17	java/util/ArrayList
    //   379: dup
    //   380: iconst_1
    //   381: invokespecial 18	java/util/ArrayList:<init>	(I)V
    //   384: astore 44
    //   386: aload 44
    //   388: ldc 98
    //   390: invokevirtual 24	java/util/ArrayList:add	(Ljava/lang/Object;)Z
    //   393: pop
    //   394: aload_0
    //   395: bipush 32
    //   397: invokestatic 78	java/lang/Integer:valueOf	(I)Ljava/lang/Integer;
    //   400: aload 44
    //   402: invokeinterface 84 3 0
    //   407: pop
    //   408: new 17	java/util/ArrayList
    //   411: dup
    //   412: iconst_1
    //   413: invokespecial 18	java/util/ArrayList:<init>	(I)V
    //   416: astore 47
    //   418: aload 47
    //   420: ldc 100
    //   422: invokevirtual 24	java/util/ArrayList:add	(Ljava/lang/Object;)Z
    //   425: pop
    //   426: aload_0
    //   427: bipush 33
    //   429: invokestatic 78	java/lang/Integer:valueOf	(I)Ljava/lang/Integer;
    //   432: aload 47
    //   434: invokeinterface 84 3 0
    //   439: pop
    //   440: new 17	java/util/ArrayList
    //   443: dup
    //   444: iconst_1
    //   445: invokespecial 18	java/util/ArrayList:<init>	(I)V
    //   448: astore 50
    //   450: aload 50
    //   452: ldc 102
    //   454: invokevirtual 24	java/util/ArrayList:add	(Ljava/lang/Object;)Z
    //   457: pop
    //   458: aload_0
    //   459: bipush 34
    //   461: invokestatic 78	java/lang/Integer:valueOf	(I)Ljava/lang/Integer;
    //   464: aload 50
    //   466: invokeinterface 84 3 0
    //   471: pop
    //   472: new 17	java/util/ArrayList
    //   475: dup
    //   476: iconst_1
    //   477: invokespecial 18	java/util/ArrayList:<init>	(I)V
    //   480: astore 53
    //   482: aload 53
    //   484: ldc 104
    //   486: invokevirtual 24	java/util/ArrayList:add	(Ljava/lang/Object;)Z
    //   489: pop
    //   490: aload_0
    //   491: bipush 36
    //   493: invokestatic 78	java/lang/Integer:valueOf	(I)Ljava/lang/Integer;
    //   496: aload 53
    //   498: invokeinterface 84 3 0
    //   503: pop
    //   504: new 17	java/util/ArrayList
    //   507: dup
    //   508: iconst_1
    //   509: invokespecial 18	java/util/ArrayList:<init>	(I)V
    //   512: astore 56
    //   514: aload 56
    //   516: ldc 106
    //   518: invokevirtual 24	java/util/ArrayList:add	(Ljava/lang/Object;)Z
    //   521: pop
    //   522: aload_0
    //   523: bipush 39
    //   525: invokestatic 78	java/lang/Integer:valueOf	(I)Ljava/lang/Integer;
    //   528: aload 56
    //   530: invokeinterface 84 3 0
    //   535: pop
    //   536: new 17	java/util/ArrayList
    //   539: dup
    //   540: iconst_1
    //   541: invokespecial 18	java/util/ArrayList:<init>	(I)V
    //   544: astore 59
    //   546: aload 59
    //   548: ldc 108
    //   550: invokevirtual 24	java/util/ArrayList:add	(Ljava/lang/Object;)Z
    //   553: pop
    //   554: aload_0
    //   555: bipush 40
    //   557: invokestatic 78	java/lang/Integer:valueOf	(I)Ljava/lang/Integer;
    //   560: aload 59
    //   562: invokeinterface 84 3 0
    //   567: pop
    //   568: new 17	java/util/ArrayList
    //   571: dup
    //   572: iconst_1
    //   573: invokespecial 18	java/util/ArrayList:<init>	(I)V
    //   576: astore 62
    //   578: aload 62
    //   580: ldc 110
    //   582: invokevirtual 24	java/util/ArrayList:add	(Ljava/lang/Object;)Z
    //   585: pop
    //   586: aload_0
    //   587: bipush 41
    //   589: invokestatic 78	java/lang/Integer:valueOf	(I)Ljava/lang/Integer;
    //   592: aload 62
    //   594: invokeinterface 84 3 0
    //   599: pop
    //   600: new 17	java/util/ArrayList
    //   603: dup
    //   604: iconst_1
    //   605: invokespecial 18	java/util/ArrayList:<init>	(I)V
    //   608: astore 65
    //   610: aload 65
    //   612: ldc 112
    //   614: invokevirtual 24	java/util/ArrayList:add	(Ljava/lang/Object;)Z
    //   617: pop
    //   618: aload_0
    //   619: bipush 43
    //   621: invokestatic 78	java/lang/Integer:valueOf	(I)Ljava/lang/Integer;
    //   624: aload 65
    //   626: invokeinterface 84 3 0
    //   631: pop
    //   632: new 17	java/util/ArrayList
    //   635: dup
    //   636: iconst_4
    //   637: invokespecial 18	java/util/ArrayList:<init>	(I)V
    //   640: astore 68
    //   642: aload 68
    //   644: ldc 114
    //   646: invokevirtual 24	java/util/ArrayList:add	(Ljava/lang/Object;)Z
    //   649: pop
    //   650: aload 68
    //   652: ldc 116
    //   654: invokevirtual 24	java/util/ArrayList:add	(Ljava/lang/Object;)Z
    //   657: pop
    //   658: aload 68
    //   660: ldc 118
    //   662: invokevirtual 24	java/util/ArrayList:add	(Ljava/lang/Object;)Z
    //   665: pop
    //   666: aload 68
    //   668: ldc 120
    //   670: invokevirtual 24	java/util/ArrayList:add	(Ljava/lang/Object;)Z
    //   673: pop
    //   674: aload_0
    //   675: bipush 44
    //   677: invokestatic 78	java/lang/Integer:valueOf	(I)Ljava/lang/Integer;
    //   680: aload 68
    //   682: invokeinterface 84 3 0
    //   687: pop
    //   688: new 17	java/util/ArrayList
    //   691: dup
    //   692: iconst_1
    //   693: invokespecial 18	java/util/ArrayList:<init>	(I)V
    //   696: astore 74
    //   698: aload 74
    //   700: ldc 122
    //   702: invokevirtual 24	java/util/ArrayList:add	(Ljava/lang/Object;)Z
    //   705: pop
    //   706: aload_0
    //   707: bipush 45
    //   709: invokestatic 78	java/lang/Integer:valueOf	(I)Ljava/lang/Integer;
    //   712: aload 74
    //   714: invokeinterface 84 3 0
    //   719: pop
    //   720: new 17	java/util/ArrayList
    //   723: dup
    //   724: iconst_1
    //   725: invokespecial 18	java/util/ArrayList:<init>	(I)V
    //   728: astore 77
    //   730: aload 77
    //   732: ldc 124
    //   734: invokevirtual 24	java/util/ArrayList:add	(Ljava/lang/Object;)Z
    //   737: pop
    //   738: aload_0
    //   739: bipush 46
    //   741: invokestatic 78	java/lang/Integer:valueOf	(I)Ljava/lang/Integer;
    //   744: aload 77
    //   746: invokeinterface 84 3 0
    //   751: pop
    //   752: new 17	java/util/ArrayList
    //   755: dup
    //   756: iconst_2
    //   757: invokespecial 18	java/util/ArrayList:<init>	(I)V
    //   760: astore 80
    //   762: aload 80
    //   764: ldc 126
    //   766: invokevirtual 24	java/util/ArrayList:add	(Ljava/lang/Object;)Z
    //   769: pop
    //   770: aload 80
    //   772: ldc 128
    //   774: invokevirtual 24	java/util/ArrayList:add	(Ljava/lang/Object;)Z
    //   777: pop
    //   778: aload_0
    //   779: bipush 47
    //   781: invokestatic 78	java/lang/Integer:valueOf	(I)Ljava/lang/Integer;
    //   784: aload 80
    //   786: invokeinterface 84 3 0
    //   791: pop
    //   792: new 17	java/util/ArrayList
    //   795: dup
    //   796: iconst_1
    //   797: invokespecial 18	java/util/ArrayList:<init>	(I)V
    //   800: astore 84
    //   802: aload 84
    //   804: ldc 130
    //   806: invokevirtual 24	java/util/ArrayList:add	(Ljava/lang/Object;)Z
    //   809: pop
    //   810: aload_0
    //   811: bipush 48
    //   813: invokestatic 78	java/lang/Integer:valueOf	(I)Ljava/lang/Integer;
    //   816: aload 84
    //   818: invokeinterface 84 3 0
    //   823: pop
    //   824: new 17	java/util/ArrayList
    //   827: dup
    //   828: iconst_1
    //   829: invokespecial 18	java/util/ArrayList:<init>	(I)V
    //   832: astore 87
    //   834: aload 87
    //   836: ldc 132
    //   838: invokevirtual 24	java/util/ArrayList:add	(Ljava/lang/Object;)Z
    //   841: pop
    //   842: aload_0
    //   843: bipush 49
    //   845: invokestatic 78	java/lang/Integer:valueOf	(I)Ljava/lang/Integer;
    //   848: aload 87
    //   850: invokeinterface 84 3 0
    //   855: pop
    //   856: new 17	java/util/ArrayList
    //   859: dup
    //   860: iconst_1
    //   861: invokespecial 18	java/util/ArrayList:<init>	(I)V
    //   864: astore 90
    //   866: aload 90
    //   868: ldc 134
    //   870: invokevirtual 24	java/util/ArrayList:add	(Ljava/lang/Object;)Z
    //   873: pop
    //   874: aload_0
    //   875: bipush 51
    //   877: invokestatic 78	java/lang/Integer:valueOf	(I)Ljava/lang/Integer;
    //   880: aload 90
    //   882: invokeinterface 84 3 0
    //   887: pop
    //   888: new 17	java/util/ArrayList
    //   891: dup
    //   892: iconst_1
    //   893: invokespecial 18	java/util/ArrayList:<init>	(I)V
    //   896: astore 93
    //   898: aload 93
    //   900: ldc 136
    //   902: invokevirtual 24	java/util/ArrayList:add	(Ljava/lang/Object;)Z
    //   905: pop
    //   906: aload_0
    //   907: bipush 52
    //   909: invokestatic 78	java/lang/Integer:valueOf	(I)Ljava/lang/Integer;
    //   912: aload 93
    //   914: invokeinterface 84 3 0
    //   919: pop
    //   920: new 17	java/util/ArrayList
    //   923: dup
    //   924: iconst_1
    //   925: invokespecial 18	java/util/ArrayList:<init>	(I)V
    //   928: astore 96
    //   930: aload 96
    //   932: ldc 138
    //   934: invokevirtual 24	java/util/ArrayList:add	(Ljava/lang/Object;)Z
    //   937: pop
    //   938: aload_0
    //   939: bipush 53
    //   941: invokestatic 78	java/lang/Integer:valueOf	(I)Ljava/lang/Integer;
    //   944: aload 96
    //   946: invokeinterface 84 3 0
    //   951: pop
    //   952: new 17	java/util/ArrayList
    //   955: dup
    //   956: iconst_1
    //   957: invokespecial 18	java/util/ArrayList:<init>	(I)V
    //   960: astore 99
    //   962: aload 99
    //   964: ldc 140
    //   966: invokevirtual 24	java/util/ArrayList:add	(Ljava/lang/Object;)Z
    //   969: pop
    //   970: aload_0
    //   971: bipush 54
    //   973: invokestatic 78	java/lang/Integer:valueOf	(I)Ljava/lang/Integer;
    //   976: aload 99
    //   978: invokeinterface 84 3 0
    //   983: pop
    //   984: new 17	java/util/ArrayList
    //   987: dup
    //   988: iconst_1
    //   989: invokespecial 18	java/util/ArrayList:<init>	(I)V
    //   992: astore 102
    //   994: aload 102
    //   996: ldc 142
    //   998: invokevirtual 24	java/util/ArrayList:add	(Ljava/lang/Object;)Z
    //   1001: pop
    //   1002: aload_0
    //   1003: bipush 55
    //   1005: invokestatic 78	java/lang/Integer:valueOf	(I)Ljava/lang/Integer;
    //   1008: aload 102
    //   1010: invokeinterface 84 3 0
    //   1015: pop
    //   1016: new 17	java/util/ArrayList
    //   1019: dup
    //   1020: iconst_1
    //   1021: invokespecial 18	java/util/ArrayList:<init>	(I)V
    //   1024: astore 105
    //   1026: aload 105
    //   1028: ldc 144
    //   1030: invokevirtual 24	java/util/ArrayList:add	(Ljava/lang/Object;)Z
    //   1033: pop
    //   1034: aload_0
    //   1035: bipush 56
    //   1037: invokestatic 78	java/lang/Integer:valueOf	(I)Ljava/lang/Integer;
    //   1040: aload 105
    //   1042: invokeinterface 84 3 0
    //   1047: pop
    //   1048: new 17	java/util/ArrayList
    //   1051: dup
    //   1052: iconst_1
    //   1053: invokespecial 18	java/util/ArrayList:<init>	(I)V
    //   1056: astore 108
    //   1058: aload 108
    //   1060: ldc 146
    //   1062: invokevirtual 24	java/util/ArrayList:add	(Ljava/lang/Object;)Z
    //   1065: pop
    //   1066: aload_0
    //   1067: bipush 57
    //   1069: invokestatic 78	java/lang/Integer:valueOf	(I)Ljava/lang/Integer;
    //   1072: aload 108
    //   1074: invokeinterface 84 3 0
    //   1079: pop
    //   1080: new 17	java/util/ArrayList
    //   1083: dup
    //   1084: iconst_1
    //   1085: invokespecial 18	java/util/ArrayList:<init>	(I)V
    //   1088: astore 111
    //   1090: aload 111
    //   1092: ldc 148
    //   1094: invokevirtual 24	java/util/ArrayList:add	(Ljava/lang/Object;)Z
    //   1097: pop
    //   1098: aload_0
    //   1099: bipush 58
    //   1101: invokestatic 78	java/lang/Integer:valueOf	(I)Ljava/lang/Integer;
    //   1104: aload 111
    //   1106: invokeinterface 84 3 0
    //   1111: pop
    //   1112: new 17	java/util/ArrayList
    //   1115: dup
    //   1116: iconst_1
    //   1117: invokespecial 18	java/util/ArrayList:<init>	(I)V
    //   1120: astore 114
    //   1122: aload 114
    //   1124: ldc 150
    //   1126: invokevirtual 24	java/util/ArrayList:add	(Ljava/lang/Object;)Z
    //   1129: pop
    //   1130: aload_0
    //   1131: bipush 60
    //   1133: invokestatic 78	java/lang/Integer:valueOf	(I)Ljava/lang/Integer;
    //   1136: aload 114
    //   1138: invokeinterface 84 3 0
    //   1143: pop
    //   1144: new 17	java/util/ArrayList
    //   1147: dup
    //   1148: iconst_3
    //   1149: invokespecial 18	java/util/ArrayList:<init>	(I)V
    //   1152: astore 117
    //   1154: aload 117
    //   1156: ldc 152
    //   1158: invokevirtual 24	java/util/ArrayList:add	(Ljava/lang/Object;)Z
    //   1161: pop
    //   1162: aload 117
    //   1164: ldc 154
    //   1166: invokevirtual 24	java/util/ArrayList:add	(Ljava/lang/Object;)Z
    //   1169: pop
    //   1170: aload 117
    //   1172: ldc 156
    //   1174: invokevirtual 24	java/util/ArrayList:add	(Ljava/lang/Object;)Z
    //   1177: pop
    //   1178: aload_0
    //   1179: bipush 61
    //   1181: invokestatic 78	java/lang/Integer:valueOf	(I)Ljava/lang/Integer;
    //   1184: aload 117
    //   1186: invokeinterface 84 3 0
    //   1191: pop
    //   1192: new 17	java/util/ArrayList
    //   1195: dup
    //   1196: iconst_1
    //   1197: invokespecial 18	java/util/ArrayList:<init>	(I)V
    //   1200: astore 122
    //   1202: aload 122
    //   1204: ldc 158
    //   1206: invokevirtual 24	java/util/ArrayList:add	(Ljava/lang/Object;)Z
    //   1209: pop
    //   1210: aload_0
    //   1211: bipush 62
    //   1213: invokestatic 78	java/lang/Integer:valueOf	(I)Ljava/lang/Integer;
    //   1216: aload 122
    //   1218: invokeinterface 84 3 0
    //   1223: pop
    //   1224: new 17	java/util/ArrayList
    //   1227: dup
    //   1228: iconst_1
    //   1229: invokespecial 18	java/util/ArrayList:<init>	(I)V
    //   1232: astore 125
    //   1234: aload 125
    //   1236: ldc 160
    //   1238: invokevirtual 24	java/util/ArrayList:add	(Ljava/lang/Object;)Z
    //   1241: pop
    //   1242: aload_0
    //   1243: bipush 63
    //   1245: invokestatic 78	java/lang/Integer:valueOf	(I)Ljava/lang/Integer;
    //   1248: aload 125
    //   1250: invokeinterface 84 3 0
    //   1255: pop
    //   1256: new 17	java/util/ArrayList
    //   1259: dup
    //   1260: iconst_1
    //   1261: invokespecial 18	java/util/ArrayList:<init>	(I)V
    //   1264: astore 128
    //   1266: aload 128
    //   1268: ldc 162
    //   1270: invokevirtual 24	java/util/ArrayList:add	(Ljava/lang/Object;)Z
    //   1273: pop
    //   1274: aload_0
    //   1275: bipush 64
    //   1277: invokestatic 78	java/lang/Integer:valueOf	(I)Ljava/lang/Integer;
    //   1280: aload 128
    //   1282: invokeinterface 84 3 0
    //   1287: pop
    //   1288: new 17	java/util/ArrayList
    //   1291: dup
    //   1292: iconst_1
    //   1293: invokespecial 18	java/util/ArrayList:<init>	(I)V
    //   1296: astore 131
    //   1298: aload 131
    //   1300: ldc 164
    //   1302: invokevirtual 24	java/util/ArrayList:add	(Ljava/lang/Object;)Z
    //   1305: pop
    //   1306: aload_0
    //   1307: bipush 65
    //   1309: invokestatic 78	java/lang/Integer:valueOf	(I)Ljava/lang/Integer;
    //   1312: aload 131
    //   1314: invokeinterface 84 3 0
    //   1319: pop
    //   1320: new 17	java/util/ArrayList
    //   1323: dup
    //   1324: iconst_1
    //   1325: invokespecial 18	java/util/ArrayList:<init>	(I)V
    //   1328: astore 134
    //   1330: aload 134
    //   1332: ldc 166
    //   1334: invokevirtual 24	java/util/ArrayList:add	(Ljava/lang/Object;)Z
    //   1337: pop
    //   1338: aload_0
    //   1339: bipush 66
    //   1341: invokestatic 78	java/lang/Integer:valueOf	(I)Ljava/lang/Integer;
    //   1344: aload 134
    //   1346: invokeinterface 84 3 0
    //   1351: pop
    //   1352: new 17	java/util/ArrayList
    //   1355: dup
    //   1356: iconst_1
    //   1357: invokespecial 18	java/util/ArrayList:<init>	(I)V
    //   1360: astore 137
    //   1362: aload 137
    //   1364: ldc 168
    //   1366: invokevirtual 24	java/util/ArrayList:add	(Ljava/lang/Object;)Z
    //   1369: pop
    //   1370: aload_0
    //   1371: bipush 81
    //   1373: invokestatic 78	java/lang/Integer:valueOf	(I)Ljava/lang/Integer;
    //   1376: aload 137
    //   1378: invokeinterface 84 3 0
    //   1383: pop
    //   1384: new 17	java/util/ArrayList
    //   1387: dup
    //   1388: iconst_1
    //   1389: invokespecial 18	java/util/ArrayList:<init>	(I)V
    //   1392: astore 140
    //   1394: aload 140
    //   1396: ldc 170
    //   1398: invokevirtual 24	java/util/ArrayList:add	(Ljava/lang/Object;)Z
    //   1401: pop
    //   1402: aload_0
    //   1403: bipush 82
    //   1405: invokestatic 78	java/lang/Integer:valueOf	(I)Ljava/lang/Integer;
    //   1408: aload 140
    //   1410: invokeinterface 84 3 0
    //   1415: pop
    //   1416: new 17	java/util/ArrayList
    //   1419: dup
    //   1420: iconst_1
    //   1421: invokespecial 18	java/util/ArrayList:<init>	(I)V
    //   1424: astore 143
    //   1426: aload 143
    //   1428: ldc 172
    //   1430: invokevirtual 24	java/util/ArrayList:add	(Ljava/lang/Object;)Z
    //   1433: pop
    //   1434: aload_0
    //   1435: bipush 84
    //   1437: invokestatic 78	java/lang/Integer:valueOf	(I)Ljava/lang/Integer;
    //   1440: aload 143
    //   1442: invokeinterface 84 3 0
    //   1447: pop
    //   1448: new 17	java/util/ArrayList
    //   1451: dup
    //   1452: iconst_1
    //   1453: invokespecial 18	java/util/ArrayList:<init>	(I)V
    //   1456: astore 146
    //   1458: aload 146
    //   1460: ldc 174
    //   1462: invokevirtual 24	java/util/ArrayList:add	(Ljava/lang/Object;)Z
    //   1465: pop
    //   1466: aload_0
    //   1467: bipush 86
    //   1469: invokestatic 78	java/lang/Integer:valueOf	(I)Ljava/lang/Integer;
    //   1472: aload 146
    //   1474: invokeinterface 84 3 0
    //   1479: pop
    //   1480: new 17	java/util/ArrayList
    //   1483: dup
    //   1484: iconst_1
    //   1485: invokespecial 18	java/util/ArrayList:<init>	(I)V
    //   1488: astore 149
    //   1490: aload 149
    //   1492: ldc 176
    //   1494: invokevirtual 24	java/util/ArrayList:add	(Ljava/lang/Object;)Z
    //   1497: pop
    //   1498: aload_0
    //   1499: bipush 90
    //   1501: invokestatic 78	java/lang/Integer:valueOf	(I)Ljava/lang/Integer;
    //   1504: aload 149
    //   1506: invokeinterface 84 3 0
    //   1511: pop
    //   1512: new 17	java/util/ArrayList
    //   1515: dup
    //   1516: iconst_1
    //   1517: invokespecial 18	java/util/ArrayList:<init>	(I)V
    //   1520: astore 152
    //   1522: aload 152
    //   1524: ldc 178
    //   1526: invokevirtual 24	java/util/ArrayList:add	(Ljava/lang/Object;)Z
    //   1529: pop
    //   1530: aload_0
    //   1531: bipush 91
    //   1533: invokestatic 78	java/lang/Integer:valueOf	(I)Ljava/lang/Integer;
    //   1536: aload 152
    //   1538: invokeinterface 84 3 0
    //   1543: pop
    //   1544: new 17	java/util/ArrayList
    //   1547: dup
    //   1548: iconst_1
    //   1549: invokespecial 18	java/util/ArrayList:<init>	(I)V
    //   1552: astore 155
    //   1554: aload 155
    //   1556: ldc 180
    //   1558: invokevirtual 24	java/util/ArrayList:add	(Ljava/lang/Object;)Z
    //   1561: pop
    //   1562: aload_0
    //   1563: bipush 92
    //   1565: invokestatic 78	java/lang/Integer:valueOf	(I)Ljava/lang/Integer;
    //   1568: aload 155
    //   1570: invokeinterface 84 3 0
    //   1575: pop
    //   1576: new 17	java/util/ArrayList
    //   1579: dup
    //   1580: iconst_1
    //   1581: invokespecial 18	java/util/ArrayList:<init>	(I)V
    //   1584: astore 158
    //   1586: aload 158
    //   1588: ldc 182
    //   1590: invokevirtual 24	java/util/ArrayList:add	(Ljava/lang/Object;)Z
    //   1593: pop
    //   1594: aload_0
    //   1595: bipush 93
    //   1597: invokestatic 78	java/lang/Integer:valueOf	(I)Ljava/lang/Integer;
    //   1600: aload 158
    //   1602: invokeinterface 84 3 0
    //   1607: pop
    //   1608: new 17	java/util/ArrayList
    //   1611: dup
    //   1612: iconst_1
    //   1613: invokespecial 18	java/util/ArrayList:<init>	(I)V
    //   1616: astore 161
    //   1618: aload 161
    //   1620: ldc 184
    //   1622: invokevirtual 24	java/util/ArrayList:add	(Ljava/lang/Object;)Z
    //   1625: pop
    //   1626: aload_0
    //   1627: bipush 94
    //   1629: invokestatic 78	java/lang/Integer:valueOf	(I)Ljava/lang/Integer;
    //   1632: aload 161
    //   1634: invokeinterface 84 3 0
    //   1639: pop
    //   1640: new 17	java/util/ArrayList
    //   1643: dup
    //   1644: iconst_1
    //   1645: invokespecial 18	java/util/ArrayList:<init>	(I)V
    //   1648: astore 164
    //   1650: aload 164
    //   1652: ldc 186
    //   1654: invokevirtual 24	java/util/ArrayList:add	(Ljava/lang/Object;)Z
    //   1657: pop
    //   1658: aload_0
    //   1659: bipush 95
    //   1661: invokestatic 78	java/lang/Integer:valueOf	(I)Ljava/lang/Integer;
    //   1664: aload 164
    //   1666: invokeinterface 84 3 0
    //   1671: pop
    //   1672: new 17	java/util/ArrayList
    //   1675: dup
    //   1676: iconst_1
    //   1677: invokespecial 18	java/util/ArrayList:<init>	(I)V
    //   1680: astore 167
    //   1682: aload 167
    //   1684: ldc 188
    //   1686: invokevirtual 24	java/util/ArrayList:add	(Ljava/lang/Object;)Z
    //   1689: pop
    //   1690: aload_0
    //   1691: bipush 98
    //   1693: invokestatic 78	java/lang/Integer:valueOf	(I)Ljava/lang/Integer;
    //   1696: aload 167
    //   1698: invokeinterface 84 3 0
    //   1703: pop
    //   1704: new 17	java/util/ArrayList
    //   1707: dup
    //   1708: iconst_1
    //   1709: invokespecial 18	java/util/ArrayList:<init>	(I)V
    //   1712: astore 170
    //   1714: aload 170
    //   1716: ldc 190
    //   1718: invokevirtual 24	java/util/ArrayList:add	(Ljava/lang/Object;)Z
    //   1721: pop
    //   1722: aload_0
    //   1723: sipush 211
    //   1726: invokestatic 78	java/lang/Integer:valueOf	(I)Ljava/lang/Integer;
    //   1729: aload 170
    //   1731: invokeinterface 84 3 0
    //   1736: pop
    //   1737: new 17	java/util/ArrayList
    //   1740: dup
    //   1741: iconst_2
    //   1742: invokespecial 18	java/util/ArrayList:<init>	(I)V
    //   1745: astore 173
    //   1747: aload 173
    //   1749: ldc 192
    //   1751: invokevirtual 24	java/util/ArrayList:add	(Ljava/lang/Object;)Z
    //   1754: pop
    //   1755: aload 173
    //   1757: ldc 194
    //   1759: invokevirtual 24	java/util/ArrayList:add	(Ljava/lang/Object;)Z
    //   1762: pop
    //   1763: aload_0
    //   1764: sipush 212
    //   1767: invokestatic 78	java/lang/Integer:valueOf	(I)Ljava/lang/Integer;
    //   1770: aload 173
    //   1772: invokeinterface 84 3 0
    //   1777: pop
    //   1778: new 17	java/util/ArrayList
    //   1781: dup
    //   1782: iconst_1
    //   1783: invokespecial 18	java/util/ArrayList:<init>	(I)V
    //   1786: astore 177
    //   1788: aload 177
    //   1790: ldc 196
    //   1792: invokevirtual 24	java/util/ArrayList:add	(Ljava/lang/Object;)Z
    //   1795: pop
    //   1796: aload_0
    //   1797: sipush 213
    //   1800: invokestatic 78	java/lang/Integer:valueOf	(I)Ljava/lang/Integer;
    //   1803: aload 177
    //   1805: invokeinterface 84 3 0
    //   1810: pop
    //   1811: new 17	java/util/ArrayList
    //   1814: dup
    //   1815: iconst_1
    //   1816: invokespecial 18	java/util/ArrayList:<init>	(I)V
    //   1819: astore 180
    //   1821: aload 180
    //   1823: ldc 198
    //   1825: invokevirtual 24	java/util/ArrayList:add	(Ljava/lang/Object;)Z
    //   1828: pop
    //   1829: aload_0
    //   1830: sipush 216
    //   1833: invokestatic 78	java/lang/Integer:valueOf	(I)Ljava/lang/Integer;
    //   1836: aload 180
    //   1838: invokeinterface 84 3 0
    //   1843: pop
    //   1844: new 17	java/util/ArrayList
    //   1847: dup
    //   1848: iconst_1
    //   1849: invokespecial 18	java/util/ArrayList:<init>	(I)V
    //   1852: astore 183
    //   1854: aload 183
    //   1856: ldc 200
    //   1858: invokevirtual 24	java/util/ArrayList:add	(Ljava/lang/Object;)Z
    //   1861: pop
    //   1862: aload_0
    //   1863: sipush 218
    //   1866: invokestatic 78	java/lang/Integer:valueOf	(I)Ljava/lang/Integer;
    //   1869: aload 183
    //   1871: invokeinterface 84 3 0
    //   1876: pop
    //   1877: new 17	java/util/ArrayList
    //   1880: dup
    //   1881: iconst_1
    //   1882: invokespecial 18	java/util/ArrayList:<init>	(I)V
    //   1885: astore 186
    //   1887: aload 186
    //   1889: ldc 202
    //   1891: invokevirtual 24	java/util/ArrayList:add	(Ljava/lang/Object;)Z
    //   1894: pop
    //   1895: aload_0
    //   1896: sipush 220
    //   1899: invokestatic 78	java/lang/Integer:valueOf	(I)Ljava/lang/Integer;
    //   1902: aload 186
    //   1904: invokeinterface 84 3 0
    //   1909: pop
    //   1910: new 17	java/util/ArrayList
    //   1913: dup
    //   1914: iconst_1
    //   1915: invokespecial 18	java/util/ArrayList:<init>	(I)V
    //   1918: astore 189
    //   1920: aload 189
    //   1922: ldc 204
    //   1924: invokevirtual 24	java/util/ArrayList:add	(Ljava/lang/Object;)Z
    //   1927: pop
    //   1928: aload_0
    //   1929: sipush 221
    //   1932: invokestatic 78	java/lang/Integer:valueOf	(I)Ljava/lang/Integer;
    //   1935: aload 189
    //   1937: invokeinterface 84 3 0
    //   1942: pop
    //   1943: new 17	java/util/ArrayList
    //   1946: dup
    //   1947: iconst_1
    //   1948: invokespecial 18	java/util/ArrayList:<init>	(I)V
    //   1951: astore 192
    //   1953: aload 192
    //   1955: ldc 206
    //   1957: invokevirtual 24	java/util/ArrayList:add	(Ljava/lang/Object;)Z
    //   1960: pop
    //   1961: aload_0
    //   1962: sipush 222
    //   1965: invokestatic 78	java/lang/Integer:valueOf	(I)Ljava/lang/Integer;
    //   1968: aload 192
    //   1970: invokeinterface 84 3 0
    //   1975: pop
    //   1976: new 17	java/util/ArrayList
    //   1979: dup
    //   1980: iconst_1
    //   1981: invokespecial 18	java/util/ArrayList:<init>	(I)V
    //   1984: astore 195
    //   1986: aload 195
    //   1988: ldc 208
    //   1990: invokevirtual 24	java/util/ArrayList:add	(Ljava/lang/Object;)Z
    //   1993: pop
    //   1994: aload_0
    //   1995: sipush 223
    //   1998: invokestatic 78	java/lang/Integer:valueOf	(I)Ljava/lang/Integer;
    //   2001: aload 195
    //   2003: invokeinterface 84 3 0
    //   2008: pop
    //   2009: new 17	java/util/ArrayList
    //   2012: dup
    //   2013: iconst_1
    //   2014: invokespecial 18	java/util/ArrayList:<init>	(I)V
    //   2017: astore 198
    //   2019: aload 198
    //   2021: ldc 210
    //   2023: invokevirtual 24	java/util/ArrayList:add	(Ljava/lang/Object;)Z
    //   2026: pop
    //   2027: aload_0
    //   2028: sipush 224
    //   2031: invokestatic 78	java/lang/Integer:valueOf	(I)Ljava/lang/Integer;
    //   2034: aload 198
    //   2036: invokeinterface 84 3 0
    //   2041: pop
    //   2042: new 17	java/util/ArrayList
    //   2045: dup
    //   2046: iconst_1
    //   2047: invokespecial 18	java/util/ArrayList:<init>	(I)V
    //   2050: astore 201
    //   2052: aload 201
    //   2054: ldc 212
    //   2056: invokevirtual 24	java/util/ArrayList:add	(Ljava/lang/Object;)Z
    //   2059: pop
    //   2060: aload_0
    //   2061: sipush 225
    //   2064: invokestatic 78	java/lang/Integer:valueOf	(I)Ljava/lang/Integer;
    //   2067: aload 201
    //   2069: invokeinterface 84 3 0
    //   2074: pop
    //   2075: new 17	java/util/ArrayList
    //   2078: dup
    //   2079: iconst_1
    //   2080: invokespecial 18	java/util/ArrayList:<init>	(I)V
    //   2083: astore 204
    //   2085: aload 204
    //   2087: ldc 214
    //   2089: invokevirtual 24	java/util/ArrayList:add	(Ljava/lang/Object;)Z
    //   2092: pop
    //   2093: aload_0
    //   2094: sipush 226
    //   2097: invokestatic 78	java/lang/Integer:valueOf	(I)Ljava/lang/Integer;
    //   2100: aload 204
    //   2102: invokeinterface 84 3 0
    //   2107: pop
    //   2108: new 17	java/util/ArrayList
    //   2111: dup
    //   2112: iconst_1
    //   2113: invokespecial 18	java/util/ArrayList:<init>	(I)V
    //   2116: astore 207
    //   2118: aload 207
    //   2120: ldc 216
    //   2122: invokevirtual 24	java/util/ArrayList:add	(Ljava/lang/Object;)Z
    //   2125: pop
    //   2126: aload_0
    //   2127: sipush 227
    //   2130: invokestatic 78	java/lang/Integer:valueOf	(I)Ljava/lang/Integer;
    //   2133: aload 207
    //   2135: invokeinterface 84 3 0
    //   2140: pop
    //   2141: new 17	java/util/ArrayList
    //   2144: dup
    //   2145: iconst_1
    //   2146: invokespecial 18	java/util/ArrayList:<init>	(I)V
    //   2149: astore 210
    //   2151: aload 210
    //   2153: ldc 218
    //   2155: invokevirtual 24	java/util/ArrayList:add	(Ljava/lang/Object;)Z
    //   2158: pop
    //   2159: aload_0
    //   2160: sipush 228
    //   2163: invokestatic 78	java/lang/Integer:valueOf	(I)Ljava/lang/Integer;
    //   2166: aload 210
    //   2168: invokeinterface 84 3 0
    //   2173: pop
    //   2174: new 17	java/util/ArrayList
    //   2177: dup
    //   2178: iconst_1
    //   2179: invokespecial 18	java/util/ArrayList:<init>	(I)V
    //   2182: astore 213
    //   2184: aload 213
    //   2186: ldc 220
    //   2188: invokevirtual 24	java/util/ArrayList:add	(Ljava/lang/Object;)Z
    //   2191: pop
    //   2192: aload_0
    //   2193: sipush 229
    //   2196: invokestatic 78	java/lang/Integer:valueOf	(I)Ljava/lang/Integer;
    //   2199: aload 213
    //   2201: invokeinterface 84 3 0
    //   2206: pop
    //   2207: new 17	java/util/ArrayList
    //   2210: dup
    //   2211: iconst_1
    //   2212: invokespecial 18	java/util/ArrayList:<init>	(I)V
    //   2215: astore 216
    //   2217: aload 216
    //   2219: ldc 222
    //   2221: invokevirtual 24	java/util/ArrayList:add	(Ljava/lang/Object;)Z
    //   2224: pop
    //   2225: aload_0
    //   2226: sipush 230
    //   2229: invokestatic 78	java/lang/Integer:valueOf	(I)Ljava/lang/Integer;
    //   2232: aload 216
    //   2234: invokeinterface 84 3 0
    //   2239: pop
    //   2240: new 17	java/util/ArrayList
    //   2243: dup
    //   2244: iconst_1
    //   2245: invokespecial 18	java/util/ArrayList:<init>	(I)V
    //   2248: astore 219
    //   2250: aload 219
    //   2252: ldc 224
    //   2254: invokevirtual 24	java/util/ArrayList:add	(Ljava/lang/Object;)Z
    //   2257: pop
    //   2258: aload_0
    //   2259: sipush 231
    //   2262: invokestatic 78	java/lang/Integer:valueOf	(I)Ljava/lang/Integer;
    //   2265: aload 219
    //   2267: invokeinterface 84 3 0
    //   2272: pop
    //   2273: new 17	java/util/ArrayList
    //   2276: dup
    //   2277: iconst_1
    //   2278: invokespecial 18	java/util/ArrayList:<init>	(I)V
    //   2281: astore 222
    //   2283: aload 222
    //   2285: ldc 226
    //   2287: invokevirtual 24	java/util/ArrayList:add	(Ljava/lang/Object;)Z
    //   2290: pop
    //   2291: aload_0
    //   2292: sipush 232
    //   2295: invokestatic 78	java/lang/Integer:valueOf	(I)Ljava/lang/Integer;
    //   2298: aload 222
    //   2300: invokeinterface 84 3 0
    //   2305: pop
    //   2306: new 17	java/util/ArrayList
    //   2309: dup
    //   2310: iconst_1
    //   2311: invokespecial 18	java/util/ArrayList:<init>	(I)V
    //   2314: astore 225
    //   2316: aload 225
    //   2318: ldc 228
    //   2320: invokevirtual 24	java/util/ArrayList:add	(Ljava/lang/Object;)Z
    //   2323: pop
    //   2324: aload_0
    //   2325: sipush 233
    //   2328: invokestatic 78	java/lang/Integer:valueOf	(I)Ljava/lang/Integer;
    //   2331: aload 225
    //   2333: invokeinterface 84 3 0
    //   2338: pop
    //   2339: new 17	java/util/ArrayList
    //   2342: dup
    //   2343: iconst_1
    //   2344: invokespecial 18	java/util/ArrayList:<init>	(I)V
    //   2347: astore 228
    //   2349: aload 228
    //   2351: ldc 230
    //   2353: invokevirtual 24	java/util/ArrayList:add	(Ljava/lang/Object;)Z
    //   2356: pop
    //   2357: aload_0
    //   2358: sipush 234
    //   2361: invokestatic 78	java/lang/Integer:valueOf	(I)Ljava/lang/Integer;
    //   2364: aload 228
    //   2366: invokeinterface 84 3 0
    //   2371: pop
    //   2372: new 17	java/util/ArrayList
    //   2375: dup
    //   2376: iconst_1
    //   2377: invokespecial 18	java/util/ArrayList:<init>	(I)V
    //   2380: astore 231
    //   2382: aload 231
    //   2384: ldc 232
    //   2386: invokevirtual 24	java/util/ArrayList:add	(Ljava/lang/Object;)Z
    //   2389: pop
    //   2390: aload_0
    //   2391: sipush 235
    //   2394: invokestatic 78	java/lang/Integer:valueOf	(I)Ljava/lang/Integer;
    //   2397: aload 231
    //   2399: invokeinterface 84 3 0
    //   2404: pop
    //   2405: new 17	java/util/ArrayList
    //   2408: dup
    //   2409: iconst_1
    //   2410: invokespecial 18	java/util/ArrayList:<init>	(I)V
    //   2413: astore 234
    //   2415: aload 234
    //   2417: ldc 234
    //   2419: invokevirtual 24	java/util/ArrayList:add	(Ljava/lang/Object;)Z
    //   2422: pop
    //   2423: aload_0
    //   2424: sipush 236
    //   2427: invokestatic 78	java/lang/Integer:valueOf	(I)Ljava/lang/Integer;
    //   2430: aload 234
    //   2432: invokeinterface 84 3 0
    //   2437: pop
    //   2438: new 17	java/util/ArrayList
    //   2441: dup
    //   2442: iconst_1
    //   2443: invokespecial 18	java/util/ArrayList:<init>	(I)V
    //   2446: astore 237
    //   2448: aload 237
    //   2450: ldc 236
    //   2452: invokevirtual 24	java/util/ArrayList:add	(Ljava/lang/Object;)Z
    //   2455: pop
    //   2456: aload_0
    //   2457: sipush 237
    //   2460: invokestatic 78	java/lang/Integer:valueOf	(I)Ljava/lang/Integer;
    //   2463: aload 237
    //   2465: invokeinterface 84 3 0
    //   2470: pop
    //   2471: new 17	java/util/ArrayList
    //   2474: dup
    //   2475: iconst_1
    //   2476: invokespecial 18	java/util/ArrayList:<init>	(I)V
    //   2479: astore 240
    //   2481: aload 240
    //   2483: ldc 238
    //   2485: invokevirtual 24	java/util/ArrayList:add	(Ljava/lang/Object;)Z
    //   2488: pop
    //   2489: aload_0
    //   2490: sipush 238
    //   2493: invokestatic 78	java/lang/Integer:valueOf	(I)Ljava/lang/Integer;
    //   2496: aload 240
    //   2498: invokeinterface 84 3 0
    //   2503: pop
    //   2504: new 17	java/util/ArrayList
    //   2507: dup
    //   2508: iconst_1
    //   2509: invokespecial 18	java/util/ArrayList:<init>	(I)V
    //   2512: astore 243
    //   2514: aload 243
    //   2516: ldc 240
    //   2518: invokevirtual 24	java/util/ArrayList:add	(Ljava/lang/Object;)Z
    //   2521: pop
    //   2522: aload_0
    //   2523: sipush 239
    //   2526: invokestatic 78	java/lang/Integer:valueOf	(I)Ljava/lang/Integer;
    //   2529: aload 243
    //   2531: invokeinterface 84 3 0
    //   2536: pop
    //   2537: new 17	java/util/ArrayList
    //   2540: dup
    //   2541: iconst_1
    //   2542: invokespecial 18	java/util/ArrayList:<init>	(I)V
    //   2545: astore 246
    //   2547: aload 246
    //   2549: ldc 242
    //   2551: invokevirtual 24	java/util/ArrayList:add	(Ljava/lang/Object;)Z
    //   2554: pop
    //   2555: aload_0
    //   2556: sipush 240
    //   2559: invokestatic 78	java/lang/Integer:valueOf	(I)Ljava/lang/Integer;
    //   2562: aload 246
    //   2564: invokeinterface 84 3 0
    //   2569: pop
    //   2570: new 17	java/util/ArrayList
    //   2573: dup
    //   2574: iconst_1
    //   2575: invokespecial 18	java/util/ArrayList:<init>	(I)V
    //   2578: astore 249
    //   2580: aload 249
    //   2582: ldc 244
    //   2584: invokevirtual 24	java/util/ArrayList:add	(Ljava/lang/Object;)Z
    //   2587: pop
    //   2588: aload_0
    //   2589: sipush 241
    //   2592: invokestatic 78	java/lang/Integer:valueOf	(I)Ljava/lang/Integer;
    //   2595: aload 249
    //   2597: invokeinterface 84 3 0
    //   2602: pop
    //   2603: new 17	java/util/ArrayList
    //   2606: dup
    //   2607: iconst_1
    //   2608: invokespecial 18	java/util/ArrayList:<init>	(I)V
    //   2611: astore 252
    //   2613: aload 252
    //   2615: ldc 246
    //   2617: invokevirtual 24	java/util/ArrayList:add	(Ljava/lang/Object;)Z
    //   2620: pop
    //   2621: aload_0
    //   2622: sipush 242
    //   2625: invokestatic 78	java/lang/Integer:valueOf	(I)Ljava/lang/Integer;
    //   2628: aload 252
    //   2630: invokeinterface 84 3 0
    //   2635: pop
    //   2636: new 17	java/util/ArrayList
    //   2639: dup
    //   2640: iconst_1
    //   2641: invokespecial 18	java/util/ArrayList:<init>	(I)V
    //   2644: astore 255
    //   2646: aload 255
    //   2648: ldc 248
    //   2650: invokevirtual 24	java/util/ArrayList:add	(Ljava/lang/Object;)Z
    //   2653: pop
    //   2654: aload_0
    //   2655: sipush 243
    //   2658: invokestatic 78	java/lang/Integer:valueOf	(I)Ljava/lang/Integer;
    //   2661: aload 255
    //   2663: invokeinterface 84 3 0
    //   2668: pop
    //   2669: new 17	java/util/ArrayList
    //   2672: dup
    //   2673: iconst_1
    //   2674: invokespecial 18	java/util/ArrayList:<init>	(I)V
    //   2677: wide
    //   2681: wide
    //   2685: ldc 250
    //   2687: invokevirtual 24	java/util/ArrayList:add	(Ljava/lang/Object;)Z
    //   2690: pop
    //   2691: aload_0
    //   2692: sipush 244
    //   2695: invokestatic 78	java/lang/Integer:valueOf	(I)Ljava/lang/Integer;
    //   2698: wide
    //   2702: invokeinterface 84 3 0
    //   2707: pop
    //   2708: new 17	java/util/ArrayList
    //   2711: dup
    //   2712: iconst_1
    //   2713: invokespecial 18	java/util/ArrayList:<init>	(I)V
    //   2716: wide
    //   2720: wide
    //   2724: ldc 252
    //   2726: invokevirtual 24	java/util/ArrayList:add	(Ljava/lang/Object;)Z
    //   2729: pop
    //   2730: aload_0
    //   2731: sipush 245
    //   2734: invokestatic 78	java/lang/Integer:valueOf	(I)Ljava/lang/Integer;
    //   2737: wide
    //   2741: invokeinterface 84 3 0
    //   2746: pop
    //   2747: new 17	java/util/ArrayList
    //   2750: dup
    //   2751: iconst_1
    //   2752: invokespecial 18	java/util/ArrayList:<init>	(I)V
    //   2755: wide
    //   2759: wide
    //   2763: ldc 254
    //   2765: invokevirtual 24	java/util/ArrayList:add	(Ljava/lang/Object;)Z
    //   2768: pop
    //   2769: aload_0
    //   2770: sipush 246
    //   2773: invokestatic 78	java/lang/Integer:valueOf	(I)Ljava/lang/Integer;
    //   2776: wide
    //   2780: invokeinterface 84 3 0
    //   2785: pop
    //   2786: new 17	java/util/ArrayList
    //   2789: dup
    //   2790: iconst_1
    //   2791: invokespecial 18	java/util/ArrayList:<init>	(I)V
    //   2794: wide
    //   2798: wide
    //   2802: ldc_w 256
    //   2805: invokevirtual 24	java/util/ArrayList:add	(Ljava/lang/Object;)Z
    //   2808: pop
    //   2809: aload_0
    //   2810: sipush 247
    //   2813: invokestatic 78	java/lang/Integer:valueOf	(I)Ljava/lang/Integer;
    //   2816: wide
    //   2820: invokeinterface 84 3 0
    //   2825: pop
    //   2826: new 17	java/util/ArrayList
    //   2829: dup
    //   2830: iconst_1
    //   2831: invokespecial 18	java/util/ArrayList:<init>	(I)V
    //   2834: wide
    //   2838: wide
    //   2842: ldc_w 258
    //   2845: invokevirtual 24	java/util/ArrayList:add	(Ljava/lang/Object;)Z
    //   2848: pop
    //   2849: aload_0
    //   2850: sipush 248
    //   2853: invokestatic 78	java/lang/Integer:valueOf	(I)Ljava/lang/Integer;
    //   2856: wide
    //   2860: invokeinterface 84 3 0
    //   2865: pop
    //   2866: new 17	java/util/ArrayList
    //   2869: dup
    //   2870: iconst_1
    //   2871: invokespecial 18	java/util/ArrayList:<init>	(I)V
    //   2874: wide
    //   2878: wide
    //   2882: ldc_w 260
    //   2885: invokevirtual 24	java/util/ArrayList:add	(Ljava/lang/Object;)Z
    //   2888: pop
    //   2889: aload_0
    //   2890: sipush 249
    //   2893: invokestatic 78	java/lang/Integer:valueOf	(I)Ljava/lang/Integer;
    //   2896: wide
    //   2900: invokeinterface 84 3 0
    //   2905: pop
    //   2906: new 17	java/util/ArrayList
    //   2909: dup
    //   2910: iconst_1
    //   2911: invokespecial 18	java/util/ArrayList:<init>	(I)V
    //   2914: wide
    //   2918: wide
    //   2922: ldc_w 262
    //   2925: invokevirtual 24	java/util/ArrayList:add	(Ljava/lang/Object;)Z
    //   2928: pop
    //   2929: aload_0
    //   2930: sipush 250
    //   2933: invokestatic 78	java/lang/Integer:valueOf	(I)Ljava/lang/Integer;
    //   2936: wide
    //   2940: invokeinterface 84 3 0
    //   2945: pop
    //   2946: new 17	java/util/ArrayList
    //   2949: dup
    //   2950: iconst_1
    //   2951: invokespecial 18	java/util/ArrayList:<init>	(I)V
    //   2954: wide
    //   2958: wide
    //   2962: ldc_w 264
    //   2965: invokevirtual 24	java/util/ArrayList:add	(Ljava/lang/Object;)Z
    //   2968: pop
    //   2969: aload_0
    //   2970: sipush 251
    //   2973: invokestatic 78	java/lang/Integer:valueOf	(I)Ljava/lang/Integer;
    //   2976: wide
    //   2980: invokeinterface 84 3 0
    //   2985: pop
    //   2986: new 17	java/util/ArrayList
    //   2989: dup
    //   2990: iconst_1
    //   2991: invokespecial 18	java/util/ArrayList:<init>	(I)V
    //   2994: wide
    //   2998: wide
    //   3002: ldc_w 266
    //   3005: invokevirtual 24	java/util/ArrayList:add	(Ljava/lang/Object;)Z
    //   3008: pop
    //   3009: aload_0
    //   3010: sipush 252
    //   3013: invokestatic 78	java/lang/Integer:valueOf	(I)Ljava/lang/Integer;
    //   3016: wide
    //   3020: invokeinterface 84 3 0
    //   3025: pop
    //   3026: new 17	java/util/ArrayList
    //   3029: dup
    //   3030: iconst_1
    //   3031: invokespecial 18	java/util/ArrayList:<init>	(I)V
    //   3034: wide
    //   3038: wide
    //   3042: ldc_w 268
    //   3045: invokevirtual 24	java/util/ArrayList:add	(Ljava/lang/Object;)Z
    //   3048: pop
    //   3049: aload_0
    //   3050: sipush 253
    //   3053: invokestatic 78	java/lang/Integer:valueOf	(I)Ljava/lang/Integer;
    //   3056: wide
    //   3060: invokeinterface 84 3 0
    //   3065: pop
    //   3066: new 17	java/util/ArrayList
    //   3069: dup
    //   3070: iconst_1
    //   3071: invokespecial 18	java/util/ArrayList:<init>	(I)V
    //   3074: wide
    //   3078: wide
    //   3082: ldc_w 270
    //   3085: invokevirtual 24	java/util/ArrayList:add	(Ljava/lang/Object;)Z
    //   3088: pop
    //   3089: aload_0
    //   3090: sipush 254
    //   3093: invokestatic 78	java/lang/Integer:valueOf	(I)Ljava/lang/Integer;
    //   3096: wide
    //   3100: invokeinterface 84 3 0
    //   3105: pop
    //   3106: new 17	java/util/ArrayList
    //   3109: dup
    //   3110: iconst_1
    //   3111: invokespecial 18	java/util/ArrayList:<init>	(I)V
    //   3114: wide
    //   3118: wide
    //   3122: ldc_w 272
    //   3125: invokevirtual 24	java/util/ArrayList:add	(Ljava/lang/Object;)Z
    //   3128: pop
    //   3129: aload_0
    //   3130: sipush 255
    //   3133: invokestatic 78	java/lang/Integer:valueOf	(I)Ljava/lang/Integer;
    //   3136: wide
    //   3140: invokeinterface 84 3 0
    //   3145: pop
    //   3146: new 17	java/util/ArrayList
    //   3149: dup
    //   3150: iconst_1
    //   3151: invokespecial 18	java/util/ArrayList:<init>	(I)V
    //   3154: wide
    //   3158: wide
    //   3162: ldc_w 274
    //   3165: invokevirtual 24	java/util/ArrayList:add	(Ljava/lang/Object;)Z
    //   3168: pop
    //   3169: aload_0
    //   3170: sipush 256
    //   3173: invokestatic 78	java/lang/Integer:valueOf	(I)Ljava/lang/Integer;
    //   3176: wide
    //   3180: invokeinterface 84 3 0
    //   3185: pop
    //   3186: new 17	java/util/ArrayList
    //   3189: dup
    //   3190: iconst_1
    //   3191: invokespecial 18	java/util/ArrayList:<init>	(I)V
    //   3194: wide
    //   3198: wide
    //   3202: ldc_w 276
    //   3205: invokevirtual 24	java/util/ArrayList:add	(Ljava/lang/Object;)Z
    //   3208: pop
    //   3209: aload_0
    //   3210: sipush 257
    //   3213: invokestatic 78	java/lang/Integer:valueOf	(I)Ljava/lang/Integer;
    //   3216: wide
    //   3220: invokeinterface 84 3 0
    //   3225: pop
    //   3226: new 17	java/util/ArrayList
    //   3229: dup
    //   3230: iconst_1
    //   3231: invokespecial 18	java/util/ArrayList:<init>	(I)V
    //   3234: wide
    //   3238: wide
    //   3242: ldc_w 278
    //   3245: invokevirtual 24	java/util/ArrayList:add	(Ljava/lang/Object;)Z
    //   3248: pop
    //   3249: aload_0
    //   3250: sipush 258
    //   3253: invokestatic 78	java/lang/Integer:valueOf	(I)Ljava/lang/Integer;
    //   3256: wide
    //   3260: invokeinterface 84 3 0
    //   3265: pop
    //   3266: new 17	java/util/ArrayList
    //   3269: dup
    //   3270: iconst_1
    //   3271: invokespecial 18	java/util/ArrayList:<init>	(I)V
    //   3274: wide
    //   3278: wide
    //   3282: ldc_w 280
    //   3285: invokevirtual 24	java/util/ArrayList:add	(Ljava/lang/Object;)Z
    //   3288: pop
    //   3289: aload_0
    //   3290: sipush 260
    //   3293: invokestatic 78	java/lang/Integer:valueOf	(I)Ljava/lang/Integer;
    //   3296: wide
    //   3300: invokeinterface 84 3 0
    //   3305: pop
    //   3306: new 17	java/util/ArrayList
    //   3309: dup
    //   3310: iconst_1
    //   3311: invokespecial 18	java/util/ArrayList:<init>	(I)V
    //   3314: wide
    //   3318: wide
    //   3322: ldc_w 282
    //   3325: invokevirtual 24	java/util/ArrayList:add	(Ljava/lang/Object;)Z
    //   3328: pop
    //   3329: aload_0
    //   3330: sipush 261
    //   3333: invokestatic 78	java/lang/Integer:valueOf	(I)Ljava/lang/Integer;
    //   3336: wide
    //   3340: invokeinterface 84 3 0
    //   3345: pop
    //   3346: new 17	java/util/ArrayList
    //   3349: dup
    //   3350: iconst_2
    //   3351: invokespecial 18	java/util/ArrayList:<init>	(I)V
    //   3354: wide
    //   3358: wide
    //   3362: ldc_w 284
    //   3365: invokevirtual 24	java/util/ArrayList:add	(Ljava/lang/Object;)Z
    //   3368: pop
    //   3369: wide
    //   3373: ldc_w 286
    //   3376: invokevirtual 24	java/util/ArrayList:add	(Ljava/lang/Object;)Z
    //   3379: pop
    //   3380: aload_0
    //   3381: sipush 262
    //   3384: invokestatic 78	java/lang/Integer:valueOf	(I)Ljava/lang/Integer;
    //   3387: wide
    //   3391: invokeinterface 84 3 0
    //   3396: pop
    //   3397: new 17	java/util/ArrayList
    //   3400: dup
    //   3401: iconst_1
    //   3402: invokespecial 18	java/util/ArrayList:<init>	(I)V
    //   3405: wide
    //   3409: wide
    //   3413: ldc_w 288
    //   3416: invokevirtual 24	java/util/ArrayList:add	(Ljava/lang/Object;)Z
    //   3419: pop
    //   3420: aload_0
    //   3421: sipush 263
    //   3424: invokestatic 78	java/lang/Integer:valueOf	(I)Ljava/lang/Integer;
    //   3427: wide
    //   3431: invokeinterface 84 3 0
    //   3436: pop
    //   3437: new 17	java/util/ArrayList
    //   3440: dup
    //   3441: iconst_1
    //   3442: invokespecial 18	java/util/ArrayList:<init>	(I)V
    //   3445: wide
    //   3449: wide
    //   3453: ldc_w 290
    //   3456: invokevirtual 24	java/util/ArrayList:add	(Ljava/lang/Object;)Z
    //   3459: pop
    //   3460: aload_0
    //   3461: sipush 264
    //   3464: invokestatic 78	java/lang/Integer:valueOf	(I)Ljava/lang/Integer;
    //   3467: wide
    //   3471: invokeinterface 84 3 0
    //   3476: pop
    //   3477: new 17	java/util/ArrayList
    //   3480: dup
    //   3481: iconst_1
    //   3482: invokespecial 18	java/util/ArrayList:<init>	(I)V
    //   3485: wide
    //   3489: wide
    //   3493: ldc_w 292
    //   3496: invokevirtual 24	java/util/ArrayList:add	(Ljava/lang/Object;)Z
    //   3499: pop
    //   3500: aload_0
    //   3501: sipush 265
    //   3504: invokestatic 78	java/lang/Integer:valueOf	(I)Ljava/lang/Integer;
    //   3507: wide
    //   3511: invokeinterface 84 3 0
    //   3516: pop
    //   3517: new 17	java/util/ArrayList
    //   3520: dup
    //   3521: iconst_1
    //   3522: invokespecial 18	java/util/ArrayList:<init>	(I)V
    //   3525: wide
    //   3529: wide
    //   3533: ldc_w 294
    //   3536: invokevirtual 24	java/util/ArrayList:add	(Ljava/lang/Object;)Z
    //   3539: pop
    //   3540: aload_0
    //   3541: sipush 266
    //   3544: invokestatic 78	java/lang/Integer:valueOf	(I)Ljava/lang/Integer;
    //   3547: wide
    //   3551: invokeinterface 84 3 0
    //   3556: pop
    //   3557: new 17	java/util/ArrayList
    //   3560: dup
    //   3561: iconst_1
    //   3562: invokespecial 18	java/util/ArrayList:<init>	(I)V
    //   3565: wide
    //   3569: wide
    //   3573: ldc_w 296
    //   3576: invokevirtual 24	java/util/ArrayList:add	(Ljava/lang/Object;)Z
    //   3579: pop
    //   3580: aload_0
    //   3581: sipush 267
    //   3584: invokestatic 78	java/lang/Integer:valueOf	(I)Ljava/lang/Integer;
    //   3587: wide
    //   3591: invokeinterface 84 3 0
    //   3596: pop
    //   3597: new 17	java/util/ArrayList
    //   3600: dup
    //   3601: iconst_1
    //   3602: invokespecial 18	java/util/ArrayList:<init>	(I)V
    //   3605: wide
    //   3609: wide
    //   3613: ldc_w 298
    //   3616: invokevirtual 24	java/util/ArrayList:add	(Ljava/lang/Object;)Z
    //   3619: pop
    //   3620: aload_0
    //   3621: sipush 268
    //   3624: invokestatic 78	java/lang/Integer:valueOf	(I)Ljava/lang/Integer;
    //   3627: wide
    //   3631: invokeinterface 84 3 0
    //   3636: pop
    //   3637: new 17	java/util/ArrayList
    //   3640: dup
    //   3641: iconst_1
    //   3642: invokespecial 18	java/util/ArrayList:<init>	(I)V
    //   3645: wide
    //   3649: wide
    //   3653: ldc_w 300
    //   3656: invokevirtual 24	java/util/ArrayList:add	(Ljava/lang/Object;)Z
    //   3659: pop
    //   3660: aload_0
    //   3661: sipush 269
    //   3664: invokestatic 78	java/lang/Integer:valueOf	(I)Ljava/lang/Integer;
    //   3667: wide
    //   3671: invokeinterface 84 3 0
    //   3676: pop
    //   3677: new 17	java/util/ArrayList
    //   3680: dup
    //   3681: iconst_2
    //   3682: invokespecial 18	java/util/ArrayList:<init>	(I)V
    //   3685: wide
    //   3689: wide
    //   3693: ldc_w 302
    //   3696: invokevirtual 24	java/util/ArrayList:add	(Ljava/lang/Object;)Z
    //   3699: pop
    //   3700: wide
    //   3704: ldc_w 304
    //   3707: invokevirtual 24	java/util/ArrayList:add	(Ljava/lang/Object;)Z
    //   3710: pop
    //   3711: aload_0
    //   3712: sipush 290
    //   3715: invokestatic 78	java/lang/Integer:valueOf	(I)Ljava/lang/Integer;
    //   3718: wide
    //   3722: invokeinterface 84 3 0
    //   3727: pop
    //   3728: new 17	java/util/ArrayList
    //   3731: dup
    //   3732: iconst_1
    //   3733: invokespecial 18	java/util/ArrayList:<init>	(I)V
    //   3736: wide
    //   3740: wide
    //   3744: ldc_w 306
    //   3747: invokevirtual 24	java/util/ArrayList:add	(Ljava/lang/Object;)Z
    //   3750: pop
    //   3751: aload_0
    //   3752: sipush 291
    //   3755: invokestatic 78	java/lang/Integer:valueOf	(I)Ljava/lang/Integer;
    //   3758: wide
    //   3762: invokeinterface 84 3 0
    //   3767: pop
    //   3768: new 17	java/util/ArrayList
    //   3771: dup
    //   3772: iconst_1
    //   3773: invokespecial 18	java/util/ArrayList:<init>	(I)V
    //   3776: wide
    //   3780: wide
    //   3784: ldc_w 308
    //   3787: invokevirtual 24	java/util/ArrayList:add	(Ljava/lang/Object;)Z
    //   3790: pop
    //   3791: aload_0
    //   3792: sipush 297
    //   3795: invokestatic 78	java/lang/Integer:valueOf	(I)Ljava/lang/Integer;
    //   3798: wide
    //   3802: invokeinterface 84 3 0
    //   3807: pop
    //   3808: new 17	java/util/ArrayList
    //   3811: dup
    //   3812: iconst_1
    //   3813: invokespecial 18	java/util/ArrayList:<init>	(I)V
    //   3816: wide
    //   3820: wide
    //   3824: ldc_w 310
    //   3827: invokevirtual 24	java/util/ArrayList:add	(Ljava/lang/Object;)Z
    //   3830: pop
    //   3831: aload_0
    //   3832: sipush 298
    //   3835: invokestatic 78	java/lang/Integer:valueOf	(I)Ljava/lang/Integer;
    //   3838: wide
    //   3842: invokeinterface 84 3 0
    //   3847: pop
    //   3848: new 17	java/util/ArrayList
    //   3851: dup
    //   3852: iconst_1
    //   3853: invokespecial 18	java/util/ArrayList:<init>	(I)V
    //   3856: wide
    //   3860: wide
    //   3864: ldc_w 312
    //   3867: invokevirtual 24	java/util/ArrayList:add	(Ljava/lang/Object;)Z
    //   3870: pop
    //   3871: aload_0
    //   3872: sipush 299
    //   3875: invokestatic 78	java/lang/Integer:valueOf	(I)Ljava/lang/Integer;
    //   3878: wide
    //   3882: invokeinterface 84 3 0
    //   3887: pop
    //   3888: new 17	java/util/ArrayList
    //   3891: dup
    //   3892: iconst_1
    //   3893: invokespecial 18	java/util/ArrayList:<init>	(I)V
    //   3896: wide
    //   3900: wide
    //   3904: ldc_w 314
    //   3907: invokevirtual 24	java/util/ArrayList:add	(Ljava/lang/Object;)Z
    //   3910: pop
    //   3911: aload_0
    //   3912: sipush 350
    //   3915: invokestatic 78	java/lang/Integer:valueOf	(I)Ljava/lang/Integer;
    //   3918: wide
    //   3922: invokeinterface 84 3 0
    //   3927: pop
    //   3928: new 17	java/util/ArrayList
    //   3931: dup
    //   3932: iconst_1
    //   3933: invokespecial 18	java/util/ArrayList:<init>	(I)V
    //   3936: wide
    //   3940: wide
    //   3944: ldc_w 316
    //   3947: invokevirtual 24	java/util/ArrayList:add	(Ljava/lang/Object;)Z
    //   3950: pop
    //   3951: aload_0
    //   3952: sipush 351
    //   3955: invokestatic 78	java/lang/Integer:valueOf	(I)Ljava/lang/Integer;
    //   3958: wide
    //   3962: invokeinterface 84 3 0
    //   3967: pop
    //   3968: new 17	java/util/ArrayList
    //   3971: dup
    //   3972: iconst_1
    //   3973: invokespecial 18	java/util/ArrayList:<init>	(I)V
    //   3976: wide
    //   3980: wide
    //   3984: ldc_w 318
    //   3987: invokevirtual 24	java/util/ArrayList:add	(Ljava/lang/Object;)Z
    //   3990: pop
    //   3991: aload_0
    //   3992: sipush 352
    //   3995: invokestatic 78	java/lang/Integer:valueOf	(I)Ljava/lang/Integer;
    //   3998: wide
    //   4002: invokeinterface 84 3 0
    //   4007: pop
    //   4008: new 17	java/util/ArrayList
    //   4011: dup
    //   4012: iconst_1
    //   4013: invokespecial 18	java/util/ArrayList:<init>	(I)V
    //   4016: wide
    //   4020: wide
    //   4024: ldc_w 320
    //   4027: invokevirtual 24	java/util/ArrayList:add	(Ljava/lang/Object;)Z
    //   4030: pop
    //   4031: aload_0
    //   4032: sipush 353
    //   4035: invokestatic 78	java/lang/Integer:valueOf	(I)Ljava/lang/Integer;
    //   4038: wide
    //   4042: invokeinterface 84 3 0
    //   4047: pop
    //   4048: new 17	java/util/ArrayList
    //   4051: dup
    //   4052: iconst_1
    //   4053: invokespecial 18	java/util/ArrayList:<init>	(I)V
    //   4056: wide
    //   4060: wide
    //   4064: ldc_w 322
    //   4067: invokevirtual 24	java/util/ArrayList:add	(Ljava/lang/Object;)Z
    //   4070: pop
    //   4071: aload_0
    //   4072: sipush 354
    //   4075: invokestatic 78	java/lang/Integer:valueOf	(I)Ljava/lang/Integer;
    //   4078: wide
    //   4082: invokeinterface 84 3 0
    //   4087: pop
    //   4088: new 17	java/util/ArrayList
    //   4091: dup
    //   4092: iconst_1
    //   4093: invokespecial 18	java/util/ArrayList:<init>	(I)V
    //   4096: wide
    //   4100: wide
    //   4104: ldc_w 324
    //   4107: invokevirtual 24	java/util/ArrayList:add	(Ljava/lang/Object;)Z
    //   4110: pop
    //   4111: aload_0
    //   4112: sipush 355
    //   4115: invokestatic 78	java/lang/Integer:valueOf	(I)Ljava/lang/Integer;
    //   4118: wide
    //   4122: invokeinterface 84 3 0
    //   4127: pop
    //   4128: new 17	java/util/ArrayList
    //   4131: dup
    //   4132: iconst_1
    //   4133: invokespecial 18	java/util/ArrayList:<init>	(I)V
    //   4136: wide
    //   4140: wide
    //   4144: ldc_w 326
    //   4147: invokevirtual 24	java/util/ArrayList:add	(Ljava/lang/Object;)Z
    //   4150: pop
    //   4151: aload_0
    //   4152: sipush 356
    //   4155: invokestatic 78	java/lang/Integer:valueOf	(I)Ljava/lang/Integer;
    //   4158: wide
    //   4162: invokeinterface 84 3 0
    //   4167: pop
    //   4168: new 17	java/util/ArrayList
    //   4171: dup
    //   4172: iconst_1
    //   4173: invokespecial 18	java/util/ArrayList:<init>	(I)V
    //   4176: wide
    //   4180: wide
    //   4184: ldc_w 328
    //   4187: invokevirtual 24	java/util/ArrayList:add	(Ljava/lang/Object;)Z
    //   4190: pop
    //   4191: aload_0
    //   4192: sipush 357
    //   4195: invokestatic 78	java/lang/Integer:valueOf	(I)Ljava/lang/Integer;
    //   4198: wide
    //   4202: invokeinterface 84 3 0
    //   4207: pop
    //   4208: new 17	java/util/ArrayList
    //   4211: dup
    //   4212: iconst_2
    //   4213: invokespecial 18	java/util/ArrayList:<init>	(I)V
    //   4216: wide
    //   4220: wide
    //   4224: ldc_w 330
    //   4227: invokevirtual 24	java/util/ArrayList:add	(Ljava/lang/Object;)Z
    //   4230: pop
    //   4231: wide
    //   4235: ldc_w 332
    //   4238: invokevirtual 24	java/util/ArrayList:add	(Ljava/lang/Object;)Z
    //   4241: pop
    //   4242: aload_0
    //   4243: sipush 358
    //   4246: invokestatic 78	java/lang/Integer:valueOf	(I)Ljava/lang/Integer;
    //   4249: wide
    //   4253: invokeinterface 84 3 0
    //   4258: pop
    //   4259: new 17	java/util/ArrayList
    //   4262: dup
    //   4263: iconst_1
    //   4264: invokespecial 18	java/util/ArrayList:<init>	(I)V
    //   4267: wide
    //   4271: wide
    //   4275: ldc_w 334
    //   4278: invokevirtual 24	java/util/ArrayList:add	(Ljava/lang/Object;)Z
    //   4281: pop
    //   4282: aload_0
    //   4283: sipush 359
    //   4286: invokestatic 78	java/lang/Integer:valueOf	(I)Ljava/lang/Integer;
    //   4289: wide
    //   4293: invokeinterface 84 3 0
    //   4298: pop
    //   4299: new 17	java/util/ArrayList
    //   4302: dup
    //   4303: iconst_1
    //   4304: invokespecial 18	java/util/ArrayList:<init>	(I)V
    //   4307: wide
    //   4311: wide
    //   4315: ldc_w 336
    //   4318: invokevirtual 24	java/util/ArrayList:add	(Ljava/lang/Object;)Z
    //   4321: pop
    //   4322: aload_0
    //   4323: sipush 370
    //   4326: invokestatic 78	java/lang/Integer:valueOf	(I)Ljava/lang/Integer;
    //   4329: wide
    //   4333: invokeinterface 84 3 0
    //   4338: pop
    //   4339: new 17	java/util/ArrayList
    //   4342: dup
    //   4343: iconst_1
    //   4344: invokespecial 18	java/util/ArrayList:<init>	(I)V
    //   4347: wide
    //   4351: wide
    //   4355: ldc_w 338
    //   4358: invokevirtual 24	java/util/ArrayList:add	(Ljava/lang/Object;)Z
    //   4361: pop
    //   4362: aload_0
    //   4363: sipush 371
    //   4366: invokestatic 78	java/lang/Integer:valueOf	(I)Ljava/lang/Integer;
    //   4369: wide
    //   4373: invokeinterface 84 3 0
    //   4378: pop
    //   4379: new 17	java/util/ArrayList
    //   4382: dup
    //   4383: iconst_1
    //   4384: invokespecial 18	java/util/ArrayList:<init>	(I)V
    //   4387: wide
    //   4391: wide
    //   4395: ldc_w 340
    //   4398: invokevirtual 24	java/util/ArrayList:add	(Ljava/lang/Object;)Z
    //   4401: pop
    //   4402: aload_0
    //   4403: sipush 372
    //   4406: invokestatic 78	java/lang/Integer:valueOf	(I)Ljava/lang/Integer;
    //   4409: wide
    //   4413: invokeinterface 84 3 0
    //   4418: pop
    //   4419: new 17	java/util/ArrayList
    //   4422: dup
    //   4423: iconst_1
    //   4424: invokespecial 18	java/util/ArrayList:<init>	(I)V
    //   4427: wide
    //   4431: wide
    //   4435: ldc_w 342
    //   4438: invokevirtual 24	java/util/ArrayList:add	(Ljava/lang/Object;)Z
    //   4441: pop
    //   4442: aload_0
    //   4443: sipush 373
    //   4446: invokestatic 78	java/lang/Integer:valueOf	(I)Ljava/lang/Integer;
    //   4449: wide
    //   4453: invokeinterface 84 3 0
    //   4458: pop
    //   4459: new 17	java/util/ArrayList
    //   4462: dup
    //   4463: iconst_1
    //   4464: invokespecial 18	java/util/ArrayList:<init>	(I)V
    //   4467: wide
    //   4471: wide
    //   4475: ldc_w 344
    //   4478: invokevirtual 24	java/util/ArrayList:add	(Ljava/lang/Object;)Z
    //   4481: pop
    //   4482: aload_0
    //   4483: sipush 374
    //   4486: invokestatic 78	java/lang/Integer:valueOf	(I)Ljava/lang/Integer;
    //   4489: wide
    //   4493: invokeinterface 84 3 0
    //   4498: pop
    //   4499: new 17	java/util/ArrayList
    //   4502: dup
    //   4503: iconst_1
    //   4504: invokespecial 18	java/util/ArrayList:<init>	(I)V
    //   4507: wide
    //   4511: wide
    //   4515: ldc_w 346
    //   4518: invokevirtual 24	java/util/ArrayList:add	(Ljava/lang/Object;)Z
    //   4521: pop
    //   4522: aload_0
    //   4523: sipush 375
    //   4526: invokestatic 78	java/lang/Integer:valueOf	(I)Ljava/lang/Integer;
    //   4529: wide
    //   4533: invokeinterface 84 3 0
    //   4538: pop
    //   4539: new 17	java/util/ArrayList
    //   4542: dup
    //   4543: iconst_1
    //   4544: invokespecial 18	java/util/ArrayList:<init>	(I)V
    //   4547: wide
    //   4551: wide
    //   4555: ldc_w 348
    //   4558: invokevirtual 24	java/util/ArrayList:add	(Ljava/lang/Object;)Z
    //   4561: pop
    //   4562: aload_0
    //   4563: sipush 376
    //   4566: invokestatic 78	java/lang/Integer:valueOf	(I)Ljava/lang/Integer;
    //   4569: wide
    //   4573: invokeinterface 84 3 0
    //   4578: pop
    //   4579: new 17	java/util/ArrayList
    //   4582: dup
    //   4583: iconst_1
    //   4584: invokespecial 18	java/util/ArrayList:<init>	(I)V
    //   4587: wide
    //   4591: wide
    //   4595: ldc_w 350
    //   4598: invokevirtual 24	java/util/ArrayList:add	(Ljava/lang/Object;)Z
    //   4601: pop
    //   4602: aload_0
    //   4603: sipush 377
    //   4606: invokestatic 78	java/lang/Integer:valueOf	(I)Ljava/lang/Integer;
    //   4609: wide
    //   4613: invokeinterface 84 3 0
    //   4618: pop
    //   4619: new 17	java/util/ArrayList
    //   4622: dup
    //   4623: iconst_1
    //   4624: invokespecial 18	java/util/ArrayList:<init>	(I)V
    //   4627: wide
    //   4631: wide
    //   4635: ldc_w 352
    //   4638: invokevirtual 24	java/util/ArrayList:add	(Ljava/lang/Object;)Z
    //   4641: pop
    //   4642: aload_0
    //   4643: sipush 378
    //   4646: invokestatic 78	java/lang/Integer:valueOf	(I)Ljava/lang/Integer;
    //   4649: wide
    //   4653: invokeinterface 84 3 0
    //   4658: pop
    //   4659: new 17	java/util/ArrayList
    //   4662: dup
    //   4663: iconst_1
    //   4664: invokespecial 18	java/util/ArrayList:<init>	(I)V
    //   4667: wide
    //   4671: wide
    //   4675: ldc_w 354
    //   4678: invokevirtual 24	java/util/ArrayList:add	(Ljava/lang/Object;)Z
    //   4681: pop
    //   4682: aload_0
    //   4683: sipush 379
    //   4686: invokestatic 78	java/lang/Integer:valueOf	(I)Ljava/lang/Integer;
    //   4689: wide
    //   4693: invokeinterface 84 3 0
    //   4698: pop
    //   4699: new 17	java/util/ArrayList
    //   4702: dup
    //   4703: iconst_1
    //   4704: invokespecial 18	java/util/ArrayList:<init>	(I)V
    //   4707: wide
    //   4711: wide
    //   4715: ldc_w 356
    //   4718: invokevirtual 24	java/util/ArrayList:add	(Ljava/lang/Object;)Z
    //   4721: pop
    //   4722: aload_0
    //   4723: sipush 380
    //   4726: invokestatic 78	java/lang/Integer:valueOf	(I)Ljava/lang/Integer;
    //   4729: wide
    //   4733: invokeinterface 84 3 0
    //   4738: pop
    //   4739: new 17	java/util/ArrayList
    //   4742: dup
    //   4743: iconst_1
    //   4744: invokespecial 18	java/util/ArrayList:<init>	(I)V
    //   4747: wide
    //   4751: wide
    //   4755: ldc_w 358
    //   4758: invokevirtual 24	java/util/ArrayList:add	(Ljava/lang/Object;)Z
    //   4761: pop
    //   4762: aload_0
    //   4763: sipush 381
    //   4766: invokestatic 78	java/lang/Integer:valueOf	(I)Ljava/lang/Integer;
    //   4769: wide
    //   4773: invokeinterface 84 3 0
    //   4778: pop
    //   4779: new 17	java/util/ArrayList
    //   4782: dup
    //   4783: iconst_1
    //   4784: invokespecial 18	java/util/ArrayList:<init>	(I)V
    //   4787: wide
    //   4791: wide
    //   4795: ldc_w 360
    //   4798: invokevirtual 24	java/util/ArrayList:add	(Ljava/lang/Object;)Z
    //   4801: pop
    //   4802: aload_0
    //   4803: sipush 382
    //   4806: invokestatic 78	java/lang/Integer:valueOf	(I)Ljava/lang/Integer;
    //   4809: wide
    //   4813: invokeinterface 84 3 0
    //   4818: pop
    //   4819: new 17	java/util/ArrayList
    //   4822: dup
    //   4823: iconst_1
    //   4824: invokespecial 18	java/util/ArrayList:<init>	(I)V
    //   4827: wide
    //   4831: wide
    //   4835: ldc_w 362
    //   4838: invokevirtual 24	java/util/ArrayList:add	(Ljava/lang/Object;)Z
    //   4841: pop
    //   4842: aload_0
    //   4843: sipush 385
    //   4846: invokestatic 78	java/lang/Integer:valueOf	(I)Ljava/lang/Integer;
    //   4849: wide
    //   4853: invokeinterface 84 3 0
    //   4858: pop
    //   4859: new 17	java/util/ArrayList
    //   4862: dup
    //   4863: iconst_1
    //   4864: invokespecial 18	java/util/ArrayList:<init>	(I)V
    //   4867: wide
    //   4871: wide
    //   4875: ldc_w 364
    //   4878: invokevirtual 24	java/util/ArrayList:add	(Ljava/lang/Object;)Z
    //   4881: pop
    //   4882: aload_0
    //   4883: sipush 386
    //   4886: invokestatic 78	java/lang/Integer:valueOf	(I)Ljava/lang/Integer;
    //   4889: wide
    //   4893: invokeinterface 84 3 0
    //   4898: pop
    //   4899: new 17	java/util/ArrayList
    //   4902: dup
    //   4903: iconst_1
    //   4904: invokespecial 18	java/util/ArrayList:<init>	(I)V
    //   4907: wide
    //   4911: wide
    //   4915: ldc_w 366
    //   4918: invokevirtual 24	java/util/ArrayList:add	(Ljava/lang/Object;)Z
    //   4921: pop
    //   4922: aload_0
    //   4923: sipush 387
    //   4926: invokestatic 78	java/lang/Integer:valueOf	(I)Ljava/lang/Integer;
    //   4929: wide
    //   4933: invokeinterface 84 3 0
    //   4938: pop
    //   4939: new 17	java/util/ArrayList
    //   4942: dup
    //   4943: iconst_1
    //   4944: invokespecial 18	java/util/ArrayList:<init>	(I)V
    //   4947: wide
    //   4951: wide
    //   4955: ldc_w 368
    //   4958: invokevirtual 24	java/util/ArrayList:add	(Ljava/lang/Object;)Z
    //   4961: pop
    //   4962: aload_0
    //   4963: sipush 389
    //   4966: invokestatic 78	java/lang/Integer:valueOf	(I)Ljava/lang/Integer;
    //   4969: wide
    //   4973: invokeinterface 84 3 0
    //   4978: pop
    //   4979: new 17	java/util/ArrayList
    //   4982: dup
    //   4983: iconst_1
    //   4984: invokespecial 18	java/util/ArrayList:<init>	(I)V
    //   4987: wide
    //   4991: wide
    //   4995: ldc_w 370
    //   4998: invokevirtual 24	java/util/ArrayList:add	(Ljava/lang/Object;)Z
    //   5001: pop
    //   5002: aload_0
    //   5003: sipush 420
    //   5006: invokestatic 78	java/lang/Integer:valueOf	(I)Ljava/lang/Integer;
    //   5009: wide
    //   5013: invokeinterface 84 3 0
    //   5018: pop
    //   5019: new 17	java/util/ArrayList
    //   5022: dup
    //   5023: iconst_1
    //   5024: invokespecial 18	java/util/ArrayList:<init>	(I)V
    //   5027: wide
    //   5031: wide
    //   5035: ldc_w 372
    //   5038: invokevirtual 24	java/util/ArrayList:add	(Ljava/lang/Object;)Z
    //   5041: pop
    //   5042: aload_0
    //   5043: sipush 421
    //   5046: invokestatic 78	java/lang/Integer:valueOf	(I)Ljava/lang/Integer;
    //   5049: wide
    //   5053: invokeinterface 84 3 0
    //   5058: pop
    //   5059: new 17	java/util/ArrayList
    //   5062: dup
    //   5063: iconst_1
    //   5064: invokespecial 18	java/util/ArrayList:<init>	(I)V
    //   5067: wide
    //   5071: wide
    //   5075: ldc_w 374
    //   5078: invokevirtual 24	java/util/ArrayList:add	(Ljava/lang/Object;)Z
    //   5081: pop
    //   5082: aload_0
    //   5083: sipush 423
    //   5086: invokestatic 78	java/lang/Integer:valueOf	(I)Ljava/lang/Integer;
    //   5089: wide
    //   5093: invokeinterface 84 3 0
    //   5098: pop
    //   5099: new 17	java/util/ArrayList
    //   5102: dup
    //   5103: iconst_1
    //   5104: invokespecial 18	java/util/ArrayList:<init>	(I)V
    //   5107: wide
    //   5111: wide
    //   5115: ldc_w 376
    //   5118: invokevirtual 24	java/util/ArrayList:add	(Ljava/lang/Object;)Z
    //   5121: pop
    //   5122: aload_0
    //   5123: sipush 500
    //   5126: invokestatic 78	java/lang/Integer:valueOf	(I)Ljava/lang/Integer;
    //   5129: wide
    //   5133: invokeinterface 84 3 0
    //   5138: pop
    //   5139: new 17	java/util/ArrayList
    //   5142: dup
    //   5143: iconst_1
    //   5144: invokespecial 18	java/util/ArrayList:<init>	(I)V
    //   5147: wide
    //   5151: wide
    //   5155: ldc_w 378
    //   5158: invokevirtual 24	java/util/ArrayList:add	(Ljava/lang/Object;)Z
    //   5161: pop
    //   5162: aload_0
    //   5163: sipush 501
    //   5166: invokestatic 78	java/lang/Integer:valueOf	(I)Ljava/lang/Integer;
    //   5169: wide
    //   5173: invokeinterface 84 3 0
    //   5178: pop
    //   5179: new 17	java/util/ArrayList
    //   5182: dup
    //   5183: iconst_1
    //   5184: invokespecial 18	java/util/ArrayList:<init>	(I)V
    //   5187: wide
    //   5191: wide
    //   5195: ldc_w 380
    //   5198: invokevirtual 24	java/util/ArrayList:add	(Ljava/lang/Object;)Z
    //   5201: pop
    //   5202: aload_0
    //   5203: sipush 502
    //   5206: invokestatic 78	java/lang/Integer:valueOf	(I)Ljava/lang/Integer;
    //   5209: wide
    //   5213: invokeinterface 84 3 0
    //   5218: pop
    //   5219: new 17	java/util/ArrayList
    //   5222: dup
    //   5223: iconst_1
    //   5224: invokespecial 18	java/util/ArrayList:<init>	(I)V
    //   5227: wide
    //   5231: wide
    //   5235: ldc_w 382
    //   5238: invokevirtual 24	java/util/ArrayList:add	(Ljava/lang/Object;)Z
    //   5241: pop
    //   5242: aload_0
    //   5243: sipush 503
    //   5246: invokestatic 78	java/lang/Integer:valueOf	(I)Ljava/lang/Integer;
    //   5249: wide
    //   5253: invokeinterface 84 3 0
    //   5258: pop
    //   5259: new 17	java/util/ArrayList
    //   5262: dup
    //   5263: iconst_1
    //   5264: invokespecial 18	java/util/ArrayList:<init>	(I)V
    //   5267: wide
    //   5271: wide
    //   5275: ldc_w 384
    //   5278: invokevirtual 24	java/util/ArrayList:add	(Ljava/lang/Object;)Z
    //   5281: pop
    //   5282: aload_0
    //   5283: sipush 504
    //   5286: invokestatic 78	java/lang/Integer:valueOf	(I)Ljava/lang/Integer;
    //   5289: wide
    //   5293: invokeinterface 84 3 0
    //   5298: pop
    //   5299: new 17	java/util/ArrayList
    //   5302: dup
    //   5303: iconst_1
    //   5304: invokespecial 18	java/util/ArrayList:<init>	(I)V
    //   5307: wide
    //   5311: wide
    //   5315: ldc_w 386
    //   5318: invokevirtual 24	java/util/ArrayList:add	(Ljava/lang/Object;)Z
    //   5321: pop
    //   5322: aload_0
    //   5323: sipush 505
    //   5326: invokestatic 78	java/lang/Integer:valueOf	(I)Ljava/lang/Integer;
    //   5329: wide
    //   5333: invokeinterface 84 3 0
    //   5338: pop
    //   5339: new 17	java/util/ArrayList
    //   5342: dup
    //   5343: iconst_1
    //   5344: invokespecial 18	java/util/ArrayList:<init>	(I)V
    //   5347: wide
    //   5351: wide
    //   5355: ldc_w 388
    //   5358: invokevirtual 24	java/util/ArrayList:add	(Ljava/lang/Object;)Z
    //   5361: pop
    //   5362: aload_0
    //   5363: sipush 506
    //   5366: invokestatic 78	java/lang/Integer:valueOf	(I)Ljava/lang/Integer;
    //   5369: wide
    //   5373: invokeinterface 84 3 0
    //   5378: pop
    //   5379: new 17	java/util/ArrayList
    //   5382: dup
    //   5383: iconst_1
    //   5384: invokespecial 18	java/util/ArrayList:<init>	(I)V
    //   5387: wide
    //   5391: wide
    //   5395: ldc_w 390
    //   5398: invokevirtual 24	java/util/ArrayList:add	(Ljava/lang/Object;)Z
    //   5401: pop
    //   5402: aload_0
    //   5403: sipush 507
    //   5406: invokestatic 78	java/lang/Integer:valueOf	(I)Ljava/lang/Integer;
    //   5409: wide
    //   5413: invokeinterface 84 3 0
    //   5418: pop
    //   5419: new 17	java/util/ArrayList
    //   5422: dup
    //   5423: iconst_1
    //   5424: invokespecial 18	java/util/ArrayList:<init>	(I)V
    //   5427: wide
    //   5431: wide
    //   5435: ldc_w 392
    //   5438: invokevirtual 24	java/util/ArrayList:add	(Ljava/lang/Object;)Z
    //   5441: pop
    //   5442: aload_0
    //   5443: sipush 508
    //   5446: invokestatic 78	java/lang/Integer:valueOf	(I)Ljava/lang/Integer;
    //   5449: wide
    //   5453: invokeinterface 84 3 0
    //   5458: pop
    //   5459: new 17	java/util/ArrayList
    //   5462: dup
    //   5463: iconst_1
    //   5464: invokespecial 18	java/util/ArrayList:<init>	(I)V
    //   5467: wide
    //   5471: wide
    //   5475: ldc_w 394
    //   5478: invokevirtual 24	java/util/ArrayList:add	(Ljava/lang/Object;)Z
    //   5481: pop
    //   5482: aload_0
    //   5483: sipush 509
    //   5486: invokestatic 78	java/lang/Integer:valueOf	(I)Ljava/lang/Integer;
    //   5489: wide
    //   5493: invokeinterface 84 3 0
    //   5498: pop
    //   5499: new 17	java/util/ArrayList
    //   5502: dup
    //   5503: iconst_3
    //   5504: invokespecial 18	java/util/ArrayList:<init>	(I)V
    //   5507: wide
    //   5511: wide
    //   5515: ldc_w 396
    //   5518: invokevirtual 24	java/util/ArrayList:add	(Ljava/lang/Object;)Z
    //   5521: pop
    //   5522: wide
    //   5526: ldc_w 398
    //   5529: invokevirtual 24	java/util/ArrayList:add	(Ljava/lang/Object;)Z
    //   5532: pop
    //   5533: wide
    //   5537: ldc_w 400
    //   5540: invokevirtual 24	java/util/ArrayList:add	(Ljava/lang/Object;)Z
    //   5543: pop
    //   5544: aload_0
    //   5545: sipush 590
    //   5548: invokestatic 78	java/lang/Integer:valueOf	(I)Ljava/lang/Integer;
    //   5551: wide
    //   5555: invokeinterface 84 3 0
    //   5560: pop
    //   5561: new 17	java/util/ArrayList
    //   5564: dup
    //   5565: iconst_1
    //   5566: invokespecial 18	java/util/ArrayList:<init>	(I)V
    //   5569: wide
    //   5573: wide
    //   5577: ldc_w 402
    //   5580: invokevirtual 24	java/util/ArrayList:add	(Ljava/lang/Object;)Z
    //   5583: pop
    //   5584: aload_0
    //   5585: sipush 591
    //   5588: invokestatic 78	java/lang/Integer:valueOf	(I)Ljava/lang/Integer;
    //   5591: wide
    //   5595: invokeinterface 84 3 0
    //   5600: pop
    //   5601: new 17	java/util/ArrayList
    //   5604: dup
    //   5605: iconst_1
    //   5606: invokespecial 18	java/util/ArrayList:<init>	(I)V
    //   5609: wide
    //   5613: wide
    //   5617: ldc_w 404
    //   5620: invokevirtual 24	java/util/ArrayList:add	(Ljava/lang/Object;)Z
    //   5623: pop
    //   5624: aload_0
    //   5625: sipush 592
    //   5628: invokestatic 78	java/lang/Integer:valueOf	(I)Ljava/lang/Integer;
    //   5631: wide
    //   5635: invokeinterface 84 3 0
    //   5640: pop
    //   5641: new 17	java/util/ArrayList
    //   5644: dup
    //   5645: iconst_1
    //   5646: invokespecial 18	java/util/ArrayList:<init>	(I)V
    //   5649: wide
    //   5653: wide
    //   5657: ldc_w 406
    //   5660: invokevirtual 24	java/util/ArrayList:add	(Ljava/lang/Object;)Z
    //   5663: pop
    //   5664: aload_0
    //   5665: sipush 593
    //   5668: invokestatic 78	java/lang/Integer:valueOf	(I)Ljava/lang/Integer;
    //   5671: wide
    //   5675: invokeinterface 84 3 0
    //   5680: pop
    //   5681: new 17	java/util/ArrayList
    //   5684: dup
    //   5685: iconst_1
    //   5686: invokespecial 18	java/util/ArrayList:<init>	(I)V
    //   5689: wide
    //   5693: wide
    //   5697: ldc_w 408
    //   5700: invokevirtual 24	java/util/ArrayList:add	(Ljava/lang/Object;)Z
    //   5703: pop
    //   5704: aload_0
    //   5705: sipush 594
    //   5708: invokestatic 78	java/lang/Integer:valueOf	(I)Ljava/lang/Integer;
    //   5711: wide
    //   5715: invokeinterface 84 3 0
    //   5720: pop
    //   5721: new 17	java/util/ArrayList
    //   5724: dup
    //   5725: iconst_1
    //   5726: invokespecial 18	java/util/ArrayList:<init>	(I)V
    //   5729: wide
    //   5733: wide
    //   5737: ldc_w 410
    //   5740: invokevirtual 24	java/util/ArrayList:add	(Ljava/lang/Object;)Z
    //   5743: pop
    //   5744: aload_0
    //   5745: sipush 595
    //   5748: invokestatic 78	java/lang/Integer:valueOf	(I)Ljava/lang/Integer;
    //   5751: wide
    //   5755: invokeinterface 84 3 0
    //   5760: pop
    //   5761: new 17	java/util/ArrayList
    //   5764: dup
    //   5765: iconst_1
    //   5766: invokespecial 18	java/util/ArrayList:<init>	(I)V
    //   5769: wide
    //   5773: wide
    //   5777: ldc_w 412
    //   5780: invokevirtual 24	java/util/ArrayList:add	(Ljava/lang/Object;)Z
    //   5783: pop
    //   5784: aload_0
    //   5785: sipush 596
    //   5788: invokestatic 78	java/lang/Integer:valueOf	(I)Ljava/lang/Integer;
    //   5791: wide
    //   5795: invokeinterface 84 3 0
    //   5800: pop
    //   5801: new 17	java/util/ArrayList
    //   5804: dup
    //   5805: iconst_1
    //   5806: invokespecial 18	java/util/ArrayList:<init>	(I)V
    //   5809: wide
    //   5813: wide
    //   5817: ldc_w 414
    //   5820: invokevirtual 24	java/util/ArrayList:add	(Ljava/lang/Object;)Z
    //   5823: pop
    //   5824: aload_0
    //   5825: sipush 597
    //   5828: invokestatic 78	java/lang/Integer:valueOf	(I)Ljava/lang/Integer;
    //   5831: wide
    //   5835: invokeinterface 84 3 0
    //   5840: pop
    //   5841: new 17	java/util/ArrayList
    //   5844: dup
    //   5845: iconst_1
    //   5846: invokespecial 18	java/util/ArrayList:<init>	(I)V
    //   5849: wide
    //   5853: wide
    //   5857: ldc_w 416
    //   5860: invokevirtual 24	java/util/ArrayList:add	(Ljava/lang/Object;)Z
    //   5863: pop
    //   5864: aload_0
    //   5865: sipush 598
    //   5868: invokestatic 78	java/lang/Integer:valueOf	(I)Ljava/lang/Integer;
    //   5871: wide
    //   5875: invokeinterface 84 3 0
    //   5880: pop
    //   5881: new 17	java/util/ArrayList
    //   5884: dup
    //   5885: iconst_2
    //   5886: invokespecial 18	java/util/ArrayList:<init>	(I)V
    //   5889: wide
    //   5893: wide
    //   5897: ldc_w 418
    //   5900: invokevirtual 24	java/util/ArrayList:add	(Ljava/lang/Object;)Z
    //   5903: pop
    //   5904: wide
    //   5908: ldc_w 420
    //   5911: invokevirtual 24	java/util/ArrayList:add	(Ljava/lang/Object;)Z
    //   5914: pop
    //   5915: aload_0
    //   5916: sipush 599
    //   5919: invokestatic 78	java/lang/Integer:valueOf	(I)Ljava/lang/Integer;
    //   5922: wide
    //   5926: invokeinterface 84 3 0
    //   5931: pop
    //   5932: new 17	java/util/ArrayList
    //   5935: dup
    //   5936: iconst_1
    //   5937: invokespecial 18	java/util/ArrayList:<init>	(I)V
    //   5940: wide
    //   5944: wide
    //   5948: ldc_w 422
    //   5951: invokevirtual 24	java/util/ArrayList:add	(Ljava/lang/Object;)Z
    //   5954: pop
    //   5955: aload_0
    //   5956: sipush 670
    //   5959: invokestatic 78	java/lang/Integer:valueOf	(I)Ljava/lang/Integer;
    //   5962: wide
    //   5966: invokeinterface 84 3 0
    //   5971: pop
    //   5972: new 17	java/util/ArrayList
    //   5975: dup
    //   5976: iconst_1
    //   5977: invokespecial 18	java/util/ArrayList:<init>	(I)V
    //   5980: wide
    //   5984: wide
    //   5988: ldc_w 424
    //   5991: invokevirtual 24	java/util/ArrayList:add	(Ljava/lang/Object;)Z
    //   5994: pop
    //   5995: aload_0
    //   5996: sipush 672
    //   5999: invokestatic 78	java/lang/Integer:valueOf	(I)Ljava/lang/Integer;
    //   6002: wide
    //   6006: invokeinterface 84 3 0
    //   6011: pop
    //   6012: new 17	java/util/ArrayList
    //   6015: dup
    //   6016: iconst_1
    //   6017: invokespecial 18	java/util/ArrayList:<init>	(I)V
    //   6020: wide
    //   6024: wide
    //   6028: ldc_w 426
    //   6031: invokevirtual 24	java/util/ArrayList:add	(Ljava/lang/Object;)Z
    //   6034: pop
    //   6035: aload_0
    //   6036: sipush 673
    //   6039: invokestatic 78	java/lang/Integer:valueOf	(I)Ljava/lang/Integer;
    //   6042: wide
    //   6046: invokeinterface 84 3 0
    //   6051: pop
    //   6052: new 17	java/util/ArrayList
    //   6055: dup
    //   6056: iconst_1
    //   6057: invokespecial 18	java/util/ArrayList:<init>	(I)V
    //   6060: wide
    //   6064: wide
    //   6068: ldc_w 428
    //   6071: invokevirtual 24	java/util/ArrayList:add	(Ljava/lang/Object;)Z
    //   6074: pop
    //   6075: aload_0
    //   6076: sipush 674
    //   6079: invokestatic 78	java/lang/Integer:valueOf	(I)Ljava/lang/Integer;
    //   6082: wide
    //   6086: invokeinterface 84 3 0
    //   6091: pop
    //   6092: new 17	java/util/ArrayList
    //   6095: dup
    //   6096: iconst_1
    //   6097: invokespecial 18	java/util/ArrayList:<init>	(I)V
    //   6100: wide
    //   6104: wide
    //   6108: ldc_w 430
    //   6111: invokevirtual 24	java/util/ArrayList:add	(Ljava/lang/Object;)Z
    //   6114: pop
    //   6115: aload_0
    //   6116: sipush 675
    //   6119: invokestatic 78	java/lang/Integer:valueOf	(I)Ljava/lang/Integer;
    //   6122: wide
    //   6126: invokeinterface 84 3 0
    //   6131: pop
    //   6132: new 17	java/util/ArrayList
    //   6135: dup
    //   6136: iconst_1
    //   6137: invokespecial 18	java/util/ArrayList:<init>	(I)V
    //   6140: wide
    //   6144: wide
    //   6148: ldc_w 432
    //   6151: invokevirtual 24	java/util/ArrayList:add	(Ljava/lang/Object;)Z
    //   6154: pop
    //   6155: aload_0
    //   6156: sipush 676
    //   6159: invokestatic 78	java/lang/Integer:valueOf	(I)Ljava/lang/Integer;
    //   6162: wide
    //   6166: invokeinterface 84 3 0
    //   6171: pop
    //   6172: new 17	java/util/ArrayList
    //   6175: dup
    //   6176: iconst_1
    //   6177: invokespecial 18	java/util/ArrayList:<init>	(I)V
    //   6180: wide
    //   6184: wide
    //   6188: ldc_w 434
    //   6191: invokevirtual 24	java/util/ArrayList:add	(Ljava/lang/Object;)Z
    //   6194: pop
    //   6195: aload_0
    //   6196: sipush 677
    //   6199: invokestatic 78	java/lang/Integer:valueOf	(I)Ljava/lang/Integer;
    //   6202: wide
    //   6206: invokeinterface 84 3 0
    //   6211: pop
    //   6212: new 17	java/util/ArrayList
    //   6215: dup
    //   6216: iconst_1
    //   6217: invokespecial 18	java/util/ArrayList:<init>	(I)V
    //   6220: wide
    //   6224: wide
    //   6228: ldc_w 436
    //   6231: invokevirtual 24	java/util/ArrayList:add	(Ljava/lang/Object;)Z
    //   6234: pop
    //   6235: aload_0
    //   6236: sipush 678
    //   6239: invokestatic 78	java/lang/Integer:valueOf	(I)Ljava/lang/Integer;
    //   6242: wide
    //   6246: invokeinterface 84 3 0
    //   6251: pop
    //   6252: new 17	java/util/ArrayList
    //   6255: dup
    //   6256: iconst_1
    //   6257: invokespecial 18	java/util/ArrayList:<init>	(I)V
    //   6260: wide
    //   6264: wide
    //   6268: ldc_w 438
    //   6271: invokevirtual 24	java/util/ArrayList:add	(Ljava/lang/Object;)Z
    //   6274: pop
    //   6275: aload_0
    //   6276: sipush 679
    //   6279: invokestatic 78	java/lang/Integer:valueOf	(I)Ljava/lang/Integer;
    //   6282: wide
    //   6286: invokeinterface 84 3 0
    //   6291: pop
    //   6292: new 17	java/util/ArrayList
    //   6295: dup
    //   6296: iconst_1
    //   6297: invokespecial 18	java/util/ArrayList:<init>	(I)V
    //   6300: wide
    //   6304: wide
    //   6308: ldc_w 440
    //   6311: invokevirtual 24	java/util/ArrayList:add	(Ljava/lang/Object;)Z
    //   6314: pop
    //   6315: aload_0
    //   6316: sipush 680
    //   6319: invokestatic 78	java/lang/Integer:valueOf	(I)Ljava/lang/Integer;
    //   6322: wide
    //   6326: invokeinterface 84 3 0
    //   6331: pop
    //   6332: new 17	java/util/ArrayList
    //   6335: dup
    //   6336: iconst_1
    //   6337: invokespecial 18	java/util/ArrayList:<init>	(I)V
    //   6340: wide
    //   6344: wide
    //   6348: ldc_w 442
    //   6351: invokevirtual 24	java/util/ArrayList:add	(Ljava/lang/Object;)Z
    //   6354: pop
    //   6355: aload_0
    //   6356: sipush 681
    //   6359: invokestatic 78	java/lang/Integer:valueOf	(I)Ljava/lang/Integer;
    //   6362: wide
    //   6366: invokeinterface 84 3 0
    //   6371: pop
    //   6372: new 17	java/util/ArrayList
    //   6375: dup
    //   6376: iconst_1
    //   6377: invokespecial 18	java/util/ArrayList:<init>	(I)V
    //   6380: wide
    //   6384: wide
    //   6388: ldc_w 444
    //   6391: invokevirtual 24	java/util/ArrayList:add	(Ljava/lang/Object;)Z
    //   6394: pop
    //   6395: aload_0
    //   6396: sipush 682
    //   6399: invokestatic 78	java/lang/Integer:valueOf	(I)Ljava/lang/Integer;
    //   6402: wide
    //   6406: invokeinterface 84 3 0
    //   6411: pop
    //   6412: new 17	java/util/ArrayList
    //   6415: dup
    //   6416: iconst_1
    //   6417: invokespecial 18	java/util/ArrayList:<init>	(I)V
    //   6420: wide
    //   6424: wide
    //   6428: ldc_w 446
    //   6431: invokevirtual 24	java/util/ArrayList:add	(Ljava/lang/Object;)Z
    //   6434: pop
    //   6435: aload_0
    //   6436: sipush 683
    //   6439: invokestatic 78	java/lang/Integer:valueOf	(I)Ljava/lang/Integer;
    //   6442: wide
    //   6446: invokeinterface 84 3 0
    //   6451: pop
    //   6452: new 17	java/util/ArrayList
    //   6455: dup
    //   6456: iconst_1
    //   6457: invokespecial 18	java/util/ArrayList:<init>	(I)V
    //   6460: wide
    //   6464: wide
    //   6468: ldc_w 448
    //   6471: invokevirtual 24	java/util/ArrayList:add	(Ljava/lang/Object;)Z
    //   6474: pop
    //   6475: aload_0
    //   6476: sipush 685
    //   6479: invokestatic 78	java/lang/Integer:valueOf	(I)Ljava/lang/Integer;
    //   6482: wide
    //   6486: invokeinterface 84 3 0
    //   6491: pop
    //   6492: new 17	java/util/ArrayList
    //   6495: dup
    //   6496: iconst_1
    //   6497: invokespecial 18	java/util/ArrayList:<init>	(I)V
    //   6500: wide
    //   6504: wide
    //   6508: ldc_w 450
    //   6511: invokevirtual 24	java/util/ArrayList:add	(Ljava/lang/Object;)Z
    //   6514: pop
    //   6515: aload_0
    //   6516: sipush 686
    //   6519: invokestatic 78	java/lang/Integer:valueOf	(I)Ljava/lang/Integer;
    //   6522: wide
    //   6526: invokeinterface 84 3 0
    //   6531: pop
    //   6532: new 17	java/util/ArrayList
    //   6535: dup
    //   6536: iconst_1
    //   6537: invokespecial 18	java/util/ArrayList:<init>	(I)V
    //   6540: wide
    //   6544: wide
    //   6548: ldc_w 452
    //   6551: invokevirtual 24	java/util/ArrayList:add	(Ljava/lang/Object;)Z
    //   6554: pop
    //   6555: aload_0
    //   6556: sipush 687
    //   6559: invokestatic 78	java/lang/Integer:valueOf	(I)Ljava/lang/Integer;
    //   6562: wide
    //   6566: invokeinterface 84 3 0
    //   6571: pop
    //   6572: new 17	java/util/ArrayList
    //   6575: dup
    //   6576: iconst_1
    //   6577: invokespecial 18	java/util/ArrayList:<init>	(I)V
    //   6580: wide
    //   6584: wide
    //   6588: ldc_w 454
    //   6591: invokevirtual 24	java/util/ArrayList:add	(Ljava/lang/Object;)Z
    //   6594: pop
    //   6595: aload_0
    //   6596: sipush 688
    //   6599: invokestatic 78	java/lang/Integer:valueOf	(I)Ljava/lang/Integer;
    //   6602: wide
    //   6606: invokeinterface 84 3 0
    //   6611: pop
    //   6612: new 17	java/util/ArrayList
    //   6615: dup
    //   6616: iconst_1
    //   6617: invokespecial 18	java/util/ArrayList:<init>	(I)V
    //   6620: wide
    //   6624: wide
    //   6628: ldc_w 456
    //   6631: invokevirtual 24	java/util/ArrayList:add	(Ljava/lang/Object;)Z
    //   6634: pop
    //   6635: aload_0
    //   6636: sipush 689
    //   6639: invokestatic 78	java/lang/Integer:valueOf	(I)Ljava/lang/Integer;
    //   6642: wide
    //   6646: invokeinterface 84 3 0
    //   6651: pop
    //   6652: new 17	java/util/ArrayList
    //   6655: dup
    //   6656: iconst_1
    //   6657: invokespecial 18	java/util/ArrayList:<init>	(I)V
    //   6660: wide
    //   6664: wide
    //   6668: ldc_w 458
    //   6671: invokevirtual 24	java/util/ArrayList:add	(Ljava/lang/Object;)Z
    //   6674: pop
    //   6675: aload_0
    //   6676: sipush 690
    //   6679: invokestatic 78	java/lang/Integer:valueOf	(I)Ljava/lang/Integer;
    //   6682: wide
    //   6686: invokeinterface 84 3 0
    //   6691: pop
    //   6692: new 17	java/util/ArrayList
    //   6695: dup
    //   6696: iconst_1
    //   6697: invokespecial 18	java/util/ArrayList:<init>	(I)V
    //   6700: wide
    //   6704: wide
    //   6708: ldc_w 460
    //   6711: invokevirtual 24	java/util/ArrayList:add	(Ljava/lang/Object;)Z
    //   6714: pop
    //   6715: aload_0
    //   6716: sipush 691
    //   6719: invokestatic 78	java/lang/Integer:valueOf	(I)Ljava/lang/Integer;
    //   6722: wide
    //   6726: invokeinterface 84 3 0
    //   6731: pop
    //   6732: new 17	java/util/ArrayList
    //   6735: dup
    //   6736: iconst_1
    //   6737: invokespecial 18	java/util/ArrayList:<init>	(I)V
    //   6740: wide
    //   6744: wide
    //   6748: ldc_w 462
    //   6751: invokevirtual 24	java/util/ArrayList:add	(Ljava/lang/Object;)Z
    //   6754: pop
    //   6755: aload_0
    //   6756: sipush 692
    //   6759: invokestatic 78	java/lang/Integer:valueOf	(I)Ljava/lang/Integer;
    //   6762: wide
    //   6766: invokeinterface 84 3 0
    //   6771: pop
    //   6772: new 17	java/util/ArrayList
    //   6775: dup
    //   6776: iconst_1
    //   6777: invokespecial 18	java/util/ArrayList:<init>	(I)V
    //   6780: wide
    //   6784: wide
    //   6788: ldc_w 464
    //   6791: invokevirtual 24	java/util/ArrayList:add	(Ljava/lang/Object;)Z
    //   6794: pop
    //   6795: aload_0
    //   6796: sipush 800
    //   6799: invokestatic 78	java/lang/Integer:valueOf	(I)Ljava/lang/Integer;
    //   6802: wide
    //   6806: invokeinterface 84 3 0
    //   6811: pop
    //   6812: new 17	java/util/ArrayList
    //   6815: dup
    //   6816: iconst_1
    //   6817: invokespecial 18	java/util/ArrayList:<init>	(I)V
    //   6820: wide
    //   6824: wide
    //   6828: ldc_w 464
    //   6831: invokevirtual 24	java/util/ArrayList:add	(Ljava/lang/Object;)Z
    //   6834: pop
    //   6835: aload_0
    //   6836: sipush 808
    //   6839: invokestatic 78	java/lang/Integer:valueOf	(I)Ljava/lang/Integer;
    //   6842: wide
    //   6846: invokeinterface 84 3 0
    //   6851: pop
    //   6852: new 17	java/util/ArrayList
    //   6855: dup
    //   6856: iconst_1
    //   6857: invokespecial 18	java/util/ArrayList:<init>	(I)V
    //   6860: wide
    //   6864: wide
    //   6868: ldc_w 466
    //   6871: invokevirtual 24	java/util/ArrayList:add	(Ljava/lang/Object;)Z
    //   6874: pop
    //   6875: aload_0
    //   6876: sipush 850
    //   6879: invokestatic 78	java/lang/Integer:valueOf	(I)Ljava/lang/Integer;
    //   6882: wide
    //   6886: invokeinterface 84 3 0
    //   6891: pop
    //   6892: new 17	java/util/ArrayList
    //   6895: dup
    //   6896: iconst_1
    //   6897: invokespecial 18	java/util/ArrayList:<init>	(I)V
    //   6900: wide
    //   6904: wide
    //   6908: ldc_w 468
    //   6911: invokevirtual 24	java/util/ArrayList:add	(Ljava/lang/Object;)Z
    //   6914: pop
    //   6915: aload_0
    //   6916: sipush 852
    //   6919: invokestatic 78	java/lang/Integer:valueOf	(I)Ljava/lang/Integer;
    //   6922: wide
    //   6926: invokeinterface 84 3 0
    //   6931: pop
    //   6932: new 17	java/util/ArrayList
    //   6935: dup
    //   6936: iconst_1
    //   6937: invokespecial 18	java/util/ArrayList:<init>	(I)V
    //   6940: wide
    //   6944: wide
    //   6948: ldc_w 470
    //   6951: invokevirtual 24	java/util/ArrayList:add	(Ljava/lang/Object;)Z
    //   6954: pop
    //   6955: aload_0
    //   6956: sipush 853
    //   6959: invokestatic 78	java/lang/Integer:valueOf	(I)Ljava/lang/Integer;
    //   6962: wide
    //   6966: invokeinterface 84 3 0
    //   6971: pop
    //   6972: new 17	java/util/ArrayList
    //   6975: dup
    //   6976: iconst_1
    //   6977: invokespecial 18	java/util/ArrayList:<init>	(I)V
    //   6980: wide
    //   6984: wide
    //   6988: ldc_w 472
    //   6991: invokevirtual 24	java/util/ArrayList:add	(Ljava/lang/Object;)Z
    //   6994: pop
    //   6995: aload_0
    //   6996: sipush 855
    //   6999: invokestatic 78	java/lang/Integer:valueOf	(I)Ljava/lang/Integer;
    //   7002: wide
    //   7006: invokeinterface 84 3 0
    //   7011: pop
    //   7012: new 17	java/util/ArrayList
    //   7015: dup
    //   7016: iconst_1
    //   7017: invokespecial 18	java/util/ArrayList:<init>	(I)V
    //   7020: wide
    //   7024: wide
    //   7028: ldc_w 474
    //   7031: invokevirtual 24	java/util/ArrayList:add	(Ljava/lang/Object;)Z
    //   7034: pop
    //   7035: aload_0
    //   7036: sipush 856
    //   7039: invokestatic 78	java/lang/Integer:valueOf	(I)Ljava/lang/Integer;
    //   7042: wide
    //   7046: invokeinterface 84 3 0
    //   7051: pop
    //   7052: new 17	java/util/ArrayList
    //   7055: dup
    //   7056: iconst_1
    //   7057: invokespecial 18	java/util/ArrayList:<init>	(I)V
    //   7060: wide
    //   7064: wide
    //   7068: ldc_w 464
    //   7071: invokevirtual 24	java/util/ArrayList:add	(Ljava/lang/Object;)Z
    //   7074: pop
    //   7075: aload_0
    //   7076: sipush 870
    //   7079: invokestatic 78	java/lang/Integer:valueOf	(I)Ljava/lang/Integer;
    //   7082: wide
    //   7086: invokeinterface 84 3 0
    //   7091: pop
    //   7092: new 17	java/util/ArrayList
    //   7095: dup
    //   7096: iconst_1
    //   7097: invokespecial 18	java/util/ArrayList:<init>	(I)V
    //   7100: wide
    //   7104: wide
    //   7108: ldc_w 464
    //   7111: invokevirtual 24	java/util/ArrayList:add	(Ljava/lang/Object;)Z
    //   7114: pop
    //   7115: aload_0
    //   7116: sipush 878
    //   7119: invokestatic 78	java/lang/Integer:valueOf	(I)Ljava/lang/Integer;
    //   7122: wide
    //   7126: invokeinterface 84 3 0
    //   7131: pop
    //   7132: new 17	java/util/ArrayList
    //   7135: dup
    //   7136: iconst_1
    //   7137: invokespecial 18	java/util/ArrayList:<init>	(I)V
    //   7140: wide
    //   7144: wide
    //   7148: ldc_w 476
    //   7151: invokevirtual 24	java/util/ArrayList:add	(Ljava/lang/Object;)Z
    //   7154: pop
    //   7155: aload_0
    //   7156: sipush 880
    //   7159: invokestatic 78	java/lang/Integer:valueOf	(I)Ljava/lang/Integer;
    //   7162: wide
    //   7166: invokeinterface 84 3 0
    //   7171: pop
    //   7172: new 17	java/util/ArrayList
    //   7175: dup
    //   7176: iconst_1
    //   7177: invokespecial 18	java/util/ArrayList:<init>	(I)V
    //   7180: wide
    //   7184: wide
    //   7188: ldc_w 464
    //   7191: invokevirtual 24	java/util/ArrayList:add	(Ljava/lang/Object;)Z
    //   7194: pop
    //   7195: aload_0
    //   7196: sipush 881
    //   7199: invokestatic 78	java/lang/Integer:valueOf	(I)Ljava/lang/Integer;
    //   7202: wide
    //   7206: invokeinterface 84 3 0
    //   7211: pop
    //   7212: new 17	java/util/ArrayList
    //   7215: dup
    //   7216: iconst_1
    //   7217: invokespecial 18	java/util/ArrayList:<init>	(I)V
    //   7220: wide
    //   7224: wide
    //   7228: ldc_w 464
    //   7231: invokevirtual 24	java/util/ArrayList:add	(Ljava/lang/Object;)Z
    //   7234: pop
    //   7235: aload_0
    //   7236: sipush 882
    //   7239: invokestatic 78	java/lang/Integer:valueOf	(I)Ljava/lang/Integer;
    //   7242: wide
    //   7246: invokeinterface 84 3 0
    //   7251: pop
    //   7252: new 17	java/util/ArrayList
    //   7255: dup
    //   7256: iconst_1
    //   7257: invokespecial 18	java/util/ArrayList:<init>	(I)V
    //   7260: wide
    //   7264: wide
    //   7268: ldc_w 464
    //   7271: invokevirtual 24	java/util/ArrayList:add	(Ljava/lang/Object;)Z
    //   7274: pop
    //   7275: aload_0
    //   7276: sipush 883
    //   7279: invokestatic 78	java/lang/Integer:valueOf	(I)Ljava/lang/Integer;
    //   7282: wide
    //   7286: invokeinterface 84 3 0
    //   7291: pop
    //   7292: new 17	java/util/ArrayList
    //   7295: dup
    //   7296: iconst_1
    //   7297: invokespecial 18	java/util/ArrayList:<init>	(I)V
    //   7300: wide
    //   7304: wide
    //   7308: ldc_w 478
    //   7311: invokevirtual 24	java/util/ArrayList:add	(Ljava/lang/Object;)Z
    //   7314: pop
    //   7315: aload_0
    //   7316: sipush 886
    //   7319: invokestatic 78	java/lang/Integer:valueOf	(I)Ljava/lang/Integer;
    //   7322: wide
    //   7326: invokeinterface 84 3 0
    //   7331: pop
    //   7332: new 17	java/util/ArrayList
    //   7335: dup
    //   7336: iconst_1
    //   7337: invokespecial 18	java/util/ArrayList:<init>	(I)V
    //   7340: wide
    //   7344: wide
    //   7348: ldc_w 464
    //   7351: invokevirtual 24	java/util/ArrayList:add	(Ljava/lang/Object;)Z
    //   7354: pop
    //   7355: aload_0
    //   7356: sipush 888
    //   7359: invokestatic 78	java/lang/Integer:valueOf	(I)Ljava/lang/Integer;
    //   7362: wide
    //   7366: invokeinterface 84 3 0
    //   7371: pop
    //   7372: new 17	java/util/ArrayList
    //   7375: dup
    //   7376: iconst_1
    //   7377: invokespecial 18	java/util/ArrayList:<init>	(I)V
    //   7380: wide
    //   7384: wide
    //   7388: ldc_w 480
    //   7391: invokevirtual 24	java/util/ArrayList:add	(Ljava/lang/Object;)Z
    //   7394: pop
    //   7395: aload_0
    //   7396: sipush 960
    //   7399: invokestatic 78	java/lang/Integer:valueOf	(I)Ljava/lang/Integer;
    //   7402: wide
    //   7406: invokeinterface 84 3 0
    //   7411: pop
    //   7412: new 17	java/util/ArrayList
    //   7415: dup
    //   7416: iconst_1
    //   7417: invokespecial 18	java/util/ArrayList:<init>	(I)V
    //   7420: wide
    //   7424: wide
    //   7428: ldc_w 482
    //   7431: invokevirtual 24	java/util/ArrayList:add	(Ljava/lang/Object;)Z
    //   7434: pop
    //   7435: aload_0
    //   7436: sipush 961
    //   7439: invokestatic 78	java/lang/Integer:valueOf	(I)Ljava/lang/Integer;
    //   7442: wide
    //   7446: invokeinterface 84 3 0
    //   7451: pop
    //   7452: new 17	java/util/ArrayList
    //   7455: dup
    //   7456: iconst_1
    //   7457: invokespecial 18	java/util/ArrayList:<init>	(I)V
    //   7460: wide
    //   7464: wide
    //   7468: ldc_w 484
    //   7471: invokevirtual 24	java/util/ArrayList:add	(Ljava/lang/Object;)Z
    //   7474: pop
    //   7475: aload_0
    //   7476: sipush 962
    //   7479: invokestatic 78	java/lang/Integer:valueOf	(I)Ljava/lang/Integer;
    //   7482: wide
    //   7486: invokeinterface 84 3 0
    //   7491: pop
    //   7492: new 17	java/util/ArrayList
    //   7495: dup
    //   7496: iconst_1
    //   7497: invokespecial 18	java/util/ArrayList:<init>	(I)V
    //   7500: wide
    //   7504: wide
    //   7508: ldc_w 486
    //   7511: invokevirtual 24	java/util/ArrayList:add	(Ljava/lang/Object;)Z
    //   7514: pop
    //   7515: aload_0
    //   7516: sipush 963
    //   7519: invokestatic 78	java/lang/Integer:valueOf	(I)Ljava/lang/Integer;
    //   7522: wide
    //   7526: invokeinterface 84 3 0
    //   7531: pop
    //   7532: new 17	java/util/ArrayList
    //   7535: dup
    //   7536: iconst_1
    //   7537: invokespecial 18	java/util/ArrayList:<init>	(I)V
    //   7540: wide
    //   7544: wide
    //   7548: ldc_w 488
    //   7551: invokevirtual 24	java/util/ArrayList:add	(Ljava/lang/Object;)Z
    //   7554: pop
    //   7555: aload_0
    //   7556: sipush 964
    //   7559: invokestatic 78	java/lang/Integer:valueOf	(I)Ljava/lang/Integer;
    //   7562: wide
    //   7566: invokeinterface 84 3 0
    //   7571: pop
    //   7572: new 17	java/util/ArrayList
    //   7575: dup
    //   7576: iconst_1
    //   7577: invokespecial 18	java/util/ArrayList:<init>	(I)V
    //   7580: wide
    //   7584: wide
    //   7588: ldc_w 490
    //   7591: invokevirtual 24	java/util/ArrayList:add	(Ljava/lang/Object;)Z
    //   7594: pop
    //   7595: aload_0
    //   7596: sipush 965
    //   7599: invokestatic 78	java/lang/Integer:valueOf	(I)Ljava/lang/Integer;
    //   7602: wide
    //   7606: invokeinterface 84 3 0
    //   7611: pop
    //   7612: new 17	java/util/ArrayList
    //   7615: dup
    //   7616: iconst_1
    //   7617: invokespecial 18	java/util/ArrayList:<init>	(I)V
    //   7620: wide
    //   7624: wide
    //   7628: ldc_w 492
    //   7631: invokevirtual 24	java/util/ArrayList:add	(Ljava/lang/Object;)Z
    //   7634: pop
    //   7635: aload_0
    //   7636: sipush 966
    //   7639: invokestatic 78	java/lang/Integer:valueOf	(I)Ljava/lang/Integer;
    //   7642: wide
    //   7646: invokeinterface 84 3 0
    //   7651: pop
    //   7652: new 17	java/util/ArrayList
    //   7655: dup
    //   7656: iconst_1
    //   7657: invokespecial 18	java/util/ArrayList:<init>	(I)V
    //   7660: wide
    //   7664: wide
    //   7668: ldc_w 494
    //   7671: invokevirtual 24	java/util/ArrayList:add	(Ljava/lang/Object;)Z
    //   7674: pop
    //   7675: aload_0
    //   7676: sipush 967
    //   7679: invokestatic 78	java/lang/Integer:valueOf	(I)Ljava/lang/Integer;
    //   7682: wide
    //   7686: invokeinterface 84 3 0
    //   7691: pop
    //   7692: new 17	java/util/ArrayList
    //   7695: dup
    //   7696: iconst_1
    //   7697: invokespecial 18	java/util/ArrayList:<init>	(I)V
    //   7700: wide
    //   7704: wide
    //   7708: ldc_w 496
    //   7711: invokevirtual 24	java/util/ArrayList:add	(Ljava/lang/Object;)Z
    //   7714: pop
    //   7715: aload_0
    //   7716: sipush 968
    //   7719: invokestatic 78	java/lang/Integer:valueOf	(I)Ljava/lang/Integer;
    //   7722: wide
    //   7726: invokeinterface 84 3 0
    //   7731: pop
    //   7732: new 17	java/util/ArrayList
    //   7735: dup
    //   7736: iconst_1
    //   7737: invokespecial 18	java/util/ArrayList:<init>	(I)V
    //   7740: wide
    //   7744: wide
    //   7748: ldc_w 498
    //   7751: invokevirtual 24	java/util/ArrayList:add	(Ljava/lang/Object;)Z
    //   7754: pop
    //   7755: aload_0
    //   7756: sipush 970
    //   7759: invokestatic 78	java/lang/Integer:valueOf	(I)Ljava/lang/Integer;
    //   7762: wide
    //   7766: invokeinterface 84 3 0
    //   7771: pop
    //   7772: new 17	java/util/ArrayList
    //   7775: dup
    //   7776: iconst_1
    //   7777: invokespecial 18	java/util/ArrayList:<init>	(I)V
    //   7780: wide
    //   7784: wide
    //   7788: ldc_w 500
    //   7791: invokevirtual 24	java/util/ArrayList:add	(Ljava/lang/Object;)Z
    //   7794: pop
    //   7795: aload_0
    //   7796: sipush 971
    //   7799: invokestatic 78	java/lang/Integer:valueOf	(I)Ljava/lang/Integer;
    //   7802: wide
    //   7806: invokeinterface 84 3 0
    //   7811: pop
    //   7812: new 17	java/util/ArrayList
    //   7815: dup
    //   7816: iconst_1
    //   7817: invokespecial 18	java/util/ArrayList:<init>	(I)V
    //   7820: wide
    //   7824: wide
    //   7828: ldc_w 502
    //   7831: invokevirtual 24	java/util/ArrayList:add	(Ljava/lang/Object;)Z
    //   7834: pop
    //   7835: aload_0
    //   7836: sipush 972
    //   7839: invokestatic 78	java/lang/Integer:valueOf	(I)Ljava/lang/Integer;
    //   7842: wide
    //   7846: invokeinterface 84 3 0
    //   7851: pop
    //   7852: new 17	java/util/ArrayList
    //   7855: dup
    //   7856: iconst_1
    //   7857: invokespecial 18	java/util/ArrayList:<init>	(I)V
    //   7860: wide
    //   7864: wide
    //   7868: ldc_w 504
    //   7871: invokevirtual 24	java/util/ArrayList:add	(Ljava/lang/Object;)Z
    //   7874: pop
    //   7875: aload_0
    //   7876: sipush 973
    //   7879: invokestatic 78	java/lang/Integer:valueOf	(I)Ljava/lang/Integer;
    //   7882: wide
    //   7886: invokeinterface 84 3 0
    //   7891: pop
    //   7892: new 17	java/util/ArrayList
    //   7895: dup
    //   7896: iconst_1
    //   7897: invokespecial 18	java/util/ArrayList:<init>	(I)V
    //   7900: wide
    //   7904: wide
    //   7908: ldc_w 506
    //   7911: invokevirtual 24	java/util/ArrayList:add	(Ljava/lang/Object;)Z
    //   7914: pop
    //   7915: aload_0
    //   7916: sipush 974
    //   7919: invokestatic 78	java/lang/Integer:valueOf	(I)Ljava/lang/Integer;
    //   7922: wide
    //   7926: invokeinterface 84 3 0
    //   7931: pop
    //   7932: new 17	java/util/ArrayList
    //   7935: dup
    //   7936: iconst_1
    //   7937: invokespecial 18	java/util/ArrayList:<init>	(I)V
    //   7940: wide
    //   7944: wide
    //   7948: ldc_w 508
    //   7951: invokevirtual 24	java/util/ArrayList:add	(Ljava/lang/Object;)Z
    //   7954: pop
    //   7955: aload_0
    //   7956: sipush 975
    //   7959: invokestatic 78	java/lang/Integer:valueOf	(I)Ljava/lang/Integer;
    //   7962: wide
    //   7966: invokeinterface 84 3 0
    //   7971: pop
    //   7972: new 17	java/util/ArrayList
    //   7975: dup
    //   7976: iconst_1
    //   7977: invokespecial 18	java/util/ArrayList:<init>	(I)V
    //   7980: wide
    //   7984: wide
    //   7988: ldc_w 510
    //   7991: invokevirtual 24	java/util/ArrayList:add	(Ljava/lang/Object;)Z
    //   7994: pop
    //   7995: aload_0
    //   7996: sipush 976
    //   7999: invokestatic 78	java/lang/Integer:valueOf	(I)Ljava/lang/Integer;
    //   8002: wide
    //   8006: invokeinterface 84 3 0
    //   8011: pop
    //   8012: new 17	java/util/ArrayList
    //   8015: dup
    //   8016: iconst_1
    //   8017: invokespecial 18	java/util/ArrayList:<init>	(I)V
    //   8020: wide
    //   8024: wide
    //   8028: ldc_w 512
    //   8031: invokevirtual 24	java/util/ArrayList:add	(Ljava/lang/Object;)Z
    //   8034: pop
    //   8035: aload_0
    //   8036: sipush 977
    //   8039: invokestatic 78	java/lang/Integer:valueOf	(I)Ljava/lang/Integer;
    //   8042: wide
    //   8046: invokeinterface 84 3 0
    //   8051: pop
    //   8052: new 17	java/util/ArrayList
    //   8055: dup
    //   8056: iconst_1
    //   8057: invokespecial 18	java/util/ArrayList:<init>	(I)V
    //   8060: wide
    //   8064: wide
    //   8068: ldc_w 464
    //   8071: invokevirtual 24	java/util/ArrayList:add	(Ljava/lang/Object;)Z
    //   8074: pop
    //   8075: aload_0
    //   8076: sipush 979
    //   8079: invokestatic 78	java/lang/Integer:valueOf	(I)Ljava/lang/Integer;
    //   8082: wide
    //   8086: invokeinterface 84 3 0
    //   8091: pop
    //   8092: new 17	java/util/ArrayList
    //   8095: dup
    //   8096: iconst_1
    //   8097: invokespecial 18	java/util/ArrayList:<init>	(I)V
    //   8100: wide
    //   8104: wide
    //   8108: ldc_w 514
    //   8111: invokevirtual 24	java/util/ArrayList:add	(Ljava/lang/Object;)Z
    //   8114: pop
    //   8115: aload_0
    //   8116: sipush 992
    //   8119: invokestatic 78	java/lang/Integer:valueOf	(I)Ljava/lang/Integer;
    //   8122: wide
    //   8126: invokeinterface 84 3 0
    //   8131: pop
    //   8132: new 17	java/util/ArrayList
    //   8135: dup
    //   8136: iconst_1
    //   8137: invokespecial 18	java/util/ArrayList:<init>	(I)V
    //   8140: wide
    //   8144: wide
    //   8148: ldc_w 516
    //   8151: invokevirtual 24	java/util/ArrayList:add	(Ljava/lang/Object;)Z
    //   8154: pop
    //   8155: aload_0
    //   8156: sipush 993
    //   8159: invokestatic 78	java/lang/Integer:valueOf	(I)Ljava/lang/Integer;
    //   8162: wide
    //   8166: invokeinterface 84 3 0
    //   8171: pop
    //   8172: new 17	java/util/ArrayList
    //   8175: dup
    //   8176: iconst_1
    //   8177: invokespecial 18	java/util/ArrayList:<init>	(I)V
    //   8180: wide
    //   8184: wide
    //   8188: ldc_w 518
    //   8191: invokevirtual 24	java/util/ArrayList:add	(Ljava/lang/Object;)Z
    //   8194: pop
    //   8195: aload_0
    //   8196: sipush 994
    //   8199: invokestatic 78	java/lang/Integer:valueOf	(I)Ljava/lang/Integer;
    //   8202: wide
    //   8206: invokeinterface 84 3 0
    //   8211: pop
    //   8212: new 17	java/util/ArrayList
    //   8215: dup
    //   8216: iconst_1
    //   8217: invokespecial 18	java/util/ArrayList:<init>	(I)V
    //   8220: wide
    //   8224: wide
    //   8228: ldc_w 520
    //   8231: invokevirtual 24	java/util/ArrayList:add	(Ljava/lang/Object;)Z
    //   8234: pop
    //   8235: aload_0
    //   8236: sipush 995
    //   8239: invokestatic 78	java/lang/Integer:valueOf	(I)Ljava/lang/Integer;
    //   8242: wide
    //   8246: invokeinterface 84 3 0
    //   8251: pop
    //   8252: new 17	java/util/ArrayList
    //   8255: dup
    //   8256: iconst_1
    //   8257: invokespecial 18	java/util/ArrayList:<init>	(I)V
    //   8260: wide
    //   8264: wide
    //   8268: ldc_w 522
    //   8271: invokevirtual 24	java/util/ArrayList:add	(Ljava/lang/Object;)Z
    //   8274: pop
    //   8275: aload_0
    //   8276: sipush 996
    //   8279: invokestatic 78	java/lang/Integer:valueOf	(I)Ljava/lang/Integer;
    //   8282: wide
    //   8286: invokeinterface 84 3 0
    //   8291: pop
    //   8292: new 17	java/util/ArrayList
    //   8295: dup
    //   8296: iconst_1
    //   8297: invokespecial 18	java/util/ArrayList:<init>	(I)V
    //   8300: wide
    //   8304: wide
    //   8308: ldc_w 524
    //   8311: invokevirtual 24	java/util/ArrayList:add	(Ljava/lang/Object;)Z
    //   8314: pop
    //   8315: aload_0
    //   8316: sipush 998
    //   8319: invokestatic 78	java/lang/Integer:valueOf	(I)Ljava/lang/Integer;
    //   8322: wide
    //   8326: invokeinterface 84 3 0
    //   8331: pop
    //   8332: aload_0
    //   8333: areturn
  }
}

/* Location:           /home/phil/workspace/glass_hello_world/libs/GlassVoice-dex2jar.jar
 * Qualified Name:     com.google.i18n.phonenumbers.CountryCodeToRegionCodeMap
 * JD-Core Version:    0.6.2
 */